{"version":2,"kind":"Article","sha256":"246af0032dea20140af1552e28b3ed16768836155f078fab01fb6a54fbc9eb0a","slug":"posts.2025.new-cookbooks","location":"/posts/2025/new-cookbooks.md","dependencies":[],"frontmatter":{"title":"Hello world, new Cookbooks!","tags":["cook-off"],"authors":[{"id":"brian-rose","nameParsed":{"literal":"Brian E. J. Rose","given":"Brian E. J.","family":"Rose"},"name":"Brian E. J. Rose","orcid":"0000-0002-9961-3821","email":"brose@albany.edu","affiliations":["UAlbany"],"url":"https://brian-rose.github.io","github":"brian-rose","bluesky":"@brianejrose.bsky.social","linkedin":"https://www.linkedin.com/in/brian-rose-37bb55106/"}],"date":"2025-01-10","content_includes_title":false,"open_access":true,"license":{"content":{"id":"CC-BY-4.0","url":"https://creativecommons.org/licenses/by/4.0/","name":"Creative Commons Attribution 4.0 International","free":true,"CC":true},"code":{"id":"Apache-2.0","url":"https://opensource.org/licenses/Apache-2.0","name":"Apache License 2.0","free":true,"osi":true}},"github":"https://github.com/projectpythia/projectpythia.github.io","affiliations":[{"id":"UAlbany","name":"University at Albany (SUNY)","department":"Atmospheric and Environmental Sciences","url":"https://www.albany.edu/daes"},{"id":"CISL","name":"NSF National Center for Atmospheric Research","department":"Computational and Information Systems Lab","url":"https://www.cisl.ucar.edu"},{"id":"Unidata","name":"NSF Unidata","url":"https://www.unidata.ucar.edu"},{"id":"Argonne","name":"Argonne National Laboratory","department":"Environmental Science Division","url":"https://www.anl.gov/evs"},{"id":"CarbonPlan","name":"CarbonPlan","url":"https://carbonplan.org"},{"id":"NVIDIA","name":"NVIDIA Corporation","url":"https://www.nvidia.com/"}],"numbering":{"title":{"offset":2}},"edit_url":"https://github.com/projectpythia/projectpythia.github.io/blob/main/portal/posts/2025/new-cookbooks.md","thumbnail":"/build/44072546f251816e78d7f96a8e154dce.png","exports":[{"format":"md","filename":"new-cookbooks.md","url":"/build/new-cookbooks-f92b5d7e5bb4b3cc332a4b0bf167fab1.md"}]},"mdast":{"type":"root","children":[{"type":"block","children":[{"type":"paragraph","position":{"start":{"line":9,"column":1},"end":{"line":9,"column":1}},"children":[{"type":"text","value":"The Project Pythia team is excited to announce the publication of new community-contributed Cookbooks from our successful ","position":{"start":{"line":9,"column":1},"end":{"line":9,"column":1}},"key":"rZ82JdDyFi"},{"type":"link","url":"https://projectpythia.org/pythia-cookoff-2024/","position":{"start":{"line":9,"column":1},"end":{"line":9,"column":1}},"children":[{"type":"text","value":"2024 Pythia Cook-Off hackathon","position":{"start":{"line":9,"column":1},"end":{"line":9,"column":1}},"key":"czEzvGyZVq"}],"urlSource":"https://projectpythia.org/pythia-cookoff-2024/","key":"h5QmpQp9fY"},{"type":"text","value":", which was held June 11 - 14 2024, at the NSF NCAR’s Mesa Lab in Boulder, Colorado and online.","position":{"start":{"line":9,"column":1},"end":{"line":9,"column":1}},"key":"WP1aPjer6M"}],"key":"a5DJ7xGIHZ"},{"type":"paragraph","position":{"start":{"line":11,"column":1},"end":{"line":11,"column":1}},"children":[{"type":"link","url":"https://cookbooks.projectpythia.org","position":{"start":{"line":11,"column":1},"end":{"line":11,"column":1}},"children":[{"type":"text","value":"Cookbooks","position":{"start":{"line":11,"column":1},"end":{"line":11,"column":1}},"key":"OwvrkbeeAE"}],"urlSource":"https://cookbooks.projectpythia.org","key":"cBuiPUvzIk"},{"type":"text","value":" are geoscience-flavored collections of tutorials, recipes, and reproducible example workflows for Python-based data analysis and visualization. Cookbooks are supported by a rich computational infrastructure enabling collaborative authoring, automated health-checking, and interactive use. Cookbooks undergo a review process, are citable by DOI, and are tested and maintained by the Project Pythia community.","position":{"start":{"line":11,"column":1},"end":{"line":11,"column":1}},"key":"m43CUy7SYT"}],"key":"jIMGSpfm2f"},{"type":"paragraph","position":{"start":{"line":13,"column":1},"end":{"line":13,"column":1}},"children":[{"type":"text","value":"It’s time to celebrate the Cook-off projects that have made it across the finish line. ","position":{"start":{"line":13,"column":1},"end":{"line":13,"column":1}},"key":"qxTWFcS1k9"},{"type":"emphasis","position":{"start":{"line":13,"column":1},"end":{"line":13,"column":1}},"children":[{"type":"link","url":"https://cookbooks.projectpythia.org","position":{"start":{"line":13,"column":1},"end":{"line":13,"column":1}},"children":[{"type":"text","value":"Watch this space!","position":{"start":{"line":13,"column":1},"end":{"line":13,"column":1}},"key":"bxZnVxzYLz"}],"urlSource":"https://cookbooks.projectpythia.org","key":"emMqDc1kPt"}],"key":"nFT0wmYVAT"},{"type":"text","value":" There are several more exciting Cookbooks still in development.","position":{"start":{"line":13,"column":1},"end":{"line":13,"column":1}},"key":"m6ab21Qi5Q"}],"key":"vEFOUZWqH3"},{"type":"heading","depth":2,"position":{"start":{"line":15,"column":1},"end":{"line":15,"column":1}},"children":[{"type":"text","value":"Cookbook round-up","position":{"start":{"line":15,"column":1},"end":{"line":15,"column":1}},"key":"WwFBjq9lN5"}],"identifier":"cookbook-round-up","label":"Cookbook round-up","html_id":"cookbook-round-up","implicit":true,"key":"UdHt3ENDiS"},{"type":"paragraph","position":{"start":{"line":17,"column":1},"end":{"line":17,"column":1}},"children":[{"type":"text","value":"Here you can find brief descriptions and links to the new (and significantly updated) books on the ","position":{"start":{"line":17,"column":1},"end":{"line":17,"column":1}},"key":"f5RtulXolV"},{"type":"link","url":"https://cookbooks.projectpythia.org","position":{"start":{"line":17,"column":1},"end":{"line":17,"column":1}},"children":[{"type":"text","value":"Pythia Cookbook Gallery","position":{"start":{"line":17,"column":1},"end":{"line":17,"column":1}},"key":"htm1sjhK8K"}],"urlSource":"https://cookbooks.projectpythia.org","key":"Tv8hW2jHXg"},{"type":"text","value":". Try also filtering the ","position":{"start":{"line":17,"column":1},"end":{"line":17,"column":1}},"key":"kddHXFF27d"},{"type":"link","url":"https://cookbooks.projectpythia.org","position":{"start":{"line":17,"column":1},"end":{"line":17,"column":1}},"children":[{"type":"text","value":"gallery","position":{"start":{"line":17,"column":1},"end":{"line":17,"column":1}},"key":"ocZyJNWh5S"}],"urlSource":"https://cookbooks.projectpythia.org","key":"gl8PmRwCYO"},{"type":"text","value":" with the new “events” dropdown menu!","position":{"start":{"line":17,"column":1},"end":{"line":17,"column":1}},"key":"MaYKG07vQG"}],"key":"iNzxOKTR9u"},{"type":"heading","depth":3,"position":{"start":{"line":19,"column":1},"end":{"line":19,"column":1}},"children":[{"type":"link","url":"https://projectpythia.org/eofs-cookbook/","position":{"start":{"line":19,"column":1},"end":{"line":19,"column":1}},"children":[{"type":"text","value":"EOFs Cookbook","position":{"start":{"line":19,"column":1},"end":{"line":19,"column":1}},"key":"far53CK1O8"}],"urlSource":"https://projectpythia.org/eofs-cookbook/","key":"JFAWt7E73y"}],"identifier":"eofs-cookbook","label":"EOFs Cookbook","html_id":"eofs-cookbook","implicit":true,"key":"d7ciOlphwJ"},{"type":"image","url":"/build/44072546f251816e78d7f96a8e154dce.png","alt":"EOF cookbook thumbnail","width":"600","align":"left","key":"BjJwFqYFi3","urlSource":"https://raw.githubusercontent.com/ProjectPythia/eofs-cookbook/main/notebooks/images/nh-slp-eofs.png"},{"type":"paragraph","position":{"start":{"line":27,"column":1},"end":{"line":27,"column":1}},"children":[{"type":"strong","position":{"start":{"line":27,"column":1},"end":{"line":27,"column":1}},"children":[{"type":"text","value":"Authors:","position":{"start":{"line":27,"column":1},"end":{"line":27,"column":1}},"key":"WvxW9GtqDu"}],"key":"du4GEfiGaI"},{"type":"text","value":" ","position":{"start":{"line":27,"column":1},"end":{"line":27,"column":1}},"key":"aF8JlTevaV"},{"type":"link","url":"https://github.com/r-ford","position":{"start":{"line":27,"column":1},"end":{"line":27,"column":1}},"children":[{"type":"text","value":"Robert Ford","position":{"start":{"line":27,"column":1},"end":{"line":27,"column":1}},"key":"OoSwvqSNKC"}],"urlSource":"https://github.com/r-ford","error":true,"key":"CNQ1bdn3UT"}],"key":"yWVruN3Y3c"},{"type":"paragraph","position":{"start":{"line":29,"column":1},"end":{"line":29,"column":1}},"children":[{"type":"cite","url":"doi:10.5281/zenodo.10909812","position":{"start":{"line":29,"column":1},"end":{"line":29,"column":1}},"children":[{"type":"text","value":"Ford & EOFs Cookbook contributors (2025)","key":"r9imWRcM6H"}],"kind":"narrative","label":"https://doi.org/10.5281/zenodo.10909812","identifier":"doi:10.5281/zenodo.10909812","enumerator":"1","key":"vj3dQbHN0r"}],"key":"YOMpKTaeec"},{"type":"paragraph","position":{"start":{"line":31,"column":1},"end":{"line":31,"column":1}},"children":[{"type":"text","value":"This Cookbook covers Empirical Orthogonal Function (EOF) analysis and its application to climate data. EOF analysis is an essential tool for studying the variability of the atmosphere-ocean system. Meteorological and oceanographic data is noisy and multidimensional, but an EOF analysis allows us to pull out patterns from the data that might otherwise be difficult to find. The goal of this cookbook is to provide background and context to the analysis alongside practical examples of carrying out the analysis using Python packages.","position":{"start":{"line":31,"column":1},"end":{"line":31,"column":1}},"key":"IhzAI64TVe"}],"key":"mNs6Y5m8yE"},{"type":"paragraph","position":{"start":{"line":33,"column":1},"end":{"line":36,"column":1}},"children":[{"type":"strong","position":{"start":{"line":33,"column":1},"end":{"line":33,"column":1}},"children":[{"type":"text","value":"Contributors:","position":{"start":{"line":33,"column":1},"end":{"line":33,"column":1}},"key":"ctUssQ5rO6"}],"key":"OBCC4iLUQF"},{"type":"text","value":"\n","position":{"start":{"line":33,"column":1},"end":{"line":33,"column":1}},"key":"je9QlYqe1A"},{"type":"link","url":"https://github.com/ProjectPythia/eofs-cookbook/graphs/contributors","children":[{"type":"image","url":"/build/1546c1bbf912ca81fc0a87dedf11b814.svg","key":"WT4RSoyKr2","urlSource":"https://contrib.rocks/image?repo=ProjectPythia/eofs-cookbook"}],"urlSource":"https://github.com/ProjectPythia/eofs-cookbook/graphs/contributors","error":true,"key":"hQ3aLMBuzO"}],"key":"FxYxaE9qiM"},{"type":"heading","depth":3,"position":{"start":{"line":38,"column":1},"end":{"line":38,"column":1}},"children":[{"type":"link","url":"https://projectpythia.org/ocean-bgc-cookbook/","position":{"start":{"line":38,"column":1},"end":{"line":38,"column":1}},"children":[{"type":"text","value":"Ocean Biogeochemistry Cookbook","position":{"start":{"line":38,"column":1},"end":{"line":38,"column":1}},"key":"lq5DYMnl5N"}],"urlSource":"https://projectpythia.org/ocean-bgc-cookbook/","key":"ePJoqWRKOF"}],"identifier":"ocean-biogeochemistry-cookbook","label":"Ocean Biogeochemistry Cookbook","html_id":"ocean-biogeochemistry-cookbook","implicit":true,"key":"MI6MEdIPIV"},{"type":"image","url":"/build/6fddce30d2698bdbe249d8da81d92707.png","alt":"Ocean Biogeochemistry Cookbook thumbnail","width":"300","align":"left","key":"AR2dMzrwVX","urlSource":"https://raw.githubusercontent.com/ProjectPythia/ocean-bgc-cookbook/main/coccolithophore_kristen_krumhardt.png"},{"type":"paragraph","position":{"start":{"line":46,"column":1},"end":{"line":46,"column":1}},"children":[{"type":"strong","position":{"start":{"line":46,"column":1},"end":{"line":46,"column":1}},"children":[{"type":"text","value":"Authors:","position":{"start":{"line":46,"column":1},"end":{"line":46,"column":1}},"key":"Bt3b13QTze"}],"key":"z9aZ8p2MzR"},{"type":"text","value":" ","position":{"start":{"line":46,"column":1},"end":{"line":46,"column":1}},"key":"pCL1PXnH8D"},{"type":"link","url":"https://github.com/rmshkv","position":{"start":{"line":46,"column":1},"end":{"line":46,"column":1}},"children":[{"type":"text","value":"Lev Romashkov","position":{"start":{"line":46,"column":1},"end":{"line":46,"column":1}},"key":"zvbbEyzlhF"}],"urlSource":"https://github.com/rmshkv","error":true,"key":"yLNbg1oAVC"},{"type":"text","value":" and ","position":{"start":{"line":46,"column":1},"end":{"line":46,"column":1}},"key":"HADQWJFgXr"},{"type":"link","url":"https://github.com/kristenkrumhardt","position":{"start":{"line":46,"column":1},"end":{"line":46,"column":1}},"children":[{"type":"text","value":"Kristen Krumhardt","position":{"start":{"line":46,"column":1},"end":{"line":46,"column":1}},"key":"y39KUXJcMi"}],"urlSource":"https://github.com/kristenkrumhardt","error":true,"key":"Mj7GPdbnde"}],"key":"qMV2PlYLuH"},{"type":"paragraph","position":{"start":{"line":48,"column":1},"end":{"line":48,"column":1}},"children":[{"type":"cite","url":"doi:10.5281/zenodo.12557198","position":{"start":{"line":48,"column":1},"end":{"line":48,"column":1}},"children":[{"type":"text","value":"Romashkov ","key":"IBNU83LE92"},{"type":"emphasis","children":[{"type":"text","value":"et al.","key":"DOo38XgnDb"}],"key":"Xh8MgGAXGE"},{"type":"text","value":" (2024)","key":"LaG3PZWOqq"}],"kind":"narrative","label":"https://doi.org/10.5281/zenodo.12557198","identifier":"doi:10.5281/zenodo.12557198","enumerator":"2","key":"pwDhUK6CP6"}],"key":"WnHcfaGSko"},{"type":"paragraph","position":{"start":{"line":50,"column":1},"end":{"line":50,"column":1}},"children":[{"type":"text","value":"This Cookbook covers working with various sources of ocean biogeochemistry data, including Community Earth System Model (CESM) output and observational data. It provides a brief introduction to some metrics important to ocean biogeochemistry, from physical quantities like temperature to biological quantities like plankton biomass. It also demonstrates some of the data science techniques used to work with this information, and provides an introduction to the relationship between modeled and observational estimates.","position":{"start":{"line":50,"column":1},"end":{"line":50,"column":1}},"key":"ErrlHfOqQ6"}],"key":"imwM9bkOo3"},{"type":"paragraph","position":{"start":{"line":52,"column":1},"end":{"line":55,"column":1}},"children":[{"type":"strong","position":{"start":{"line":52,"column":1},"end":{"line":52,"column":1}},"children":[{"type":"text","value":"Contributors:","position":{"start":{"line":52,"column":1},"end":{"line":52,"column":1}},"key":"GJu0OuONHD"}],"key":"PEuBLMrkWa"},{"type":"text","value":"\n","position":{"start":{"line":52,"column":1},"end":{"line":52,"column":1}},"key":"Wj6fbkMdsf"},{"type":"link","url":"https://github.com/rmshkv/ocean-bgc-cookbook/graphs/contributors","children":[{"type":"image","url":"/build/fc211b2386cfaa5b15e5e264855f5d33.svg","key":"Z1SGV8rb9e","urlSource":"https://contrib.rocks/image?repo=rmshkv/ocean-bgc-cookbook"}],"urlSource":"https://github.com/rmshkv/ocean-bgc-cookbook/graphs/contributors","error":true,"key":"EqZQUMqFgE"}],"key":"uFwn6OYIKQ"},{"type":"heading","depth":3,"position":{"start":{"line":57,"column":1},"end":{"line":57,"column":1}},"children":[{"type":"link","url":"https://projectpythia.org/paleoPCA-cookbook/","position":{"start":{"line":57,"column":1},"end":{"line":57,"column":1}},"children":[{"type":"text","value":"Investigating interhemispheric precipitation changes over the past millennium","position":{"start":{"line":57,"column":1},"end":{"line":57,"column":1}},"key":"jDxZt6tnD0"}],"urlSource":"https://projectpythia.org/paleoPCA-cookbook/","key":"bCvEbdJ101"}],"identifier":"investigating-interhemispheric-precipitation-changes-over-the-past-millennium","label":"Investigating interhemispheric precipitation changes over the past millennium","html_id":"investigating-interhemispheric-precipitation-changes-over-the-past-millennium","implicit":true,"key":"CepEse6pIJ"},{"type":"image","url":"/build/b6dd08ff06b9c5ec16f1f385c57ee97f.png","alt":"LinkedEarth Logo","width":"400","align":"left","key":"kDycIlIhsc","urlSource":"https://raw.githubusercontent.com/LinkedEarth/Logos/master/LinkedEarth/LinkedEarth_medium.png"},{"type":"paragraph","position":{"start":{"line":65,"column":1},"end":{"line":65,"column":1}},"children":[{"type":"strong","position":{"start":{"line":65,"column":1},"end":{"line":65,"column":1}},"children":[{"type":"text","value":"Authors:","position":{"start":{"line":65,"column":1},"end":{"line":65,"column":1}},"key":"LXoEVC8QjH"}],"key":"GltL2nF7TE"},{"type":"text","value":" ","position":{"start":{"line":65,"column":1},"end":{"line":65,"column":1}},"key":"MFhTTAp8bs"},{"type":"link","url":"https://github.com/khider","position":{"start":{"line":65,"column":1},"end":{"line":65,"column":1}},"children":[{"type":"text","value":"Deborah Khider","position":{"start":{"line":65,"column":1},"end":{"line":65,"column":1}},"key":"TA9CQhxHS9"}],"urlSource":"https://github.com/khider","error":true,"key":"JmAZ1x3eOR"},{"type":"text","value":", ","position":{"start":{"line":65,"column":1},"end":{"line":65,"column":1}},"key":"kQZFMr4Xss"},{"type":"link","url":"https://github.com/sriharisundar","position":{"start":{"line":65,"column":1},"end":{"line":65,"column":1}},"children":[{"type":"text","value":"Hari Sundar","position":{"start":{"line":65,"column":1},"end":{"line":65,"column":1}},"key":"Bo0n4e7zL6"}],"urlSource":"https://github.com/sriharisundar","error":true,"key":"SLOqEamMVu"},{"type":"text","value":", and ","position":{"start":{"line":65,"column":1},"end":{"line":65,"column":1}},"key":"oVgOtu1c2T"},{"type":"link","url":"https://github.com/varunratnakar","position":{"start":{"line":65,"column":1},"end":{"line":65,"column":1}},"children":[{"type":"text","value":"Varun Ratnakar","position":{"start":{"line":65,"column":1},"end":{"line":65,"column":1}},"key":"Q8J7qmAiV2"}],"urlSource":"https://github.com/varunratnakar","error":true,"key":"ZVcF8Talkd"}],"key":"kju8H5WYWy"},{"type":"paragraph","position":{"start":{"line":67,"column":1},"end":{"line":67,"column":1}},"children":[{"type":"cite","url":"doi:10.5281/zenodo.11659789","position":{"start":{"line":67,"column":1},"end":{"line":67,"column":1}},"children":[{"type":"text","value":"Khider ","key":"uKUcx2D5Mk"},{"type":"emphasis","children":[{"type":"text","value":"et al.","key":"sgVSIvK4OX"}],"key":"AcFUWZcgdH"},{"type":"text","value":" (2024)","key":"Nb0niwbL9g"}],"kind":"narrative","label":"https://doi.org/10.5281/zenodo.11659789","identifier":"doi:10.5281/zenodo.11659789","enumerator":"3","key":"OEjTGULFYm"}],"key":"OdqAq0DtnL"},{"type":"paragraph","position":{"start":{"line":69,"column":1},"end":{"line":69,"column":1}},"children":[{"type":"text","value":"This Cookbook covers paleoclimate model-data comparison using spatio-temporal pattern obtained using Principal Component Analysis (PCA).","position":{"start":{"line":69,"column":1},"end":{"line":69,"column":1}},"key":"bxKb5GTDFn"}],"key":"frXAcoecx0"},{"type":"paragraph","position":{"start":{"line":71,"column":1},"end":{"line":71,"column":1}},"children":[{"type":"text","value":"Paleoclimate observations obtained from tree rings or the geochemical composition of speleothems, ice and sediments provide an out-of-sample validation of climate models. However, comparing the output of climate models directly with the paleoclimate observations is difficult: (1) they are often expressed in different quantities (i.e., temperature vs ring width), (2) paleoclimate observations have large time uncertainties, (3) paleoclimate observations often incorporate more than one environmental signal (i.e., temperature AND moisture).","position":{"start":{"line":71,"column":1},"end":{"line":71,"column":1}},"key":"GB5ab6vOU8"}],"key":"dtNg375EIP"},{"type":"paragraph","position":{"start":{"line":73,"column":1},"end":{"line":73,"column":1}},"children":[{"type":"text","value":"Recently, ","position":{"start":{"line":73,"column":1},"end":{"line":73,"column":1}},"key":"mJ74uHkZZ4"},{"type":"cite","url":"https://doi.org/10.1073/pnas.2120015119","position":{"start":{"line":73,"column":1},"end":{"line":73,"column":1}},"children":[{"type":"text","value":"Steinman et al. (2022)","position":{"start":{"line":73,"column":1},"end":{"line":73,"column":1}},"key":"dGYYiZywg5"}],"kind":"narrative","label":"Steinman_2022","identifier":"https://doi.org/10.1073/pnas.2120015119","enumerator":"4","key":"knHmbfXao2"},{"type":"text","value":" used PCA analysis to compare model and data output. Here, we use a similar approach with the ","position":{"start":{"line":73,"column":1},"end":{"line":73,"column":1}},"key":"V26y4bzQbe"},{"type":"link","url":"https://www.cesm.ucar.edu/community-projects/lme","position":{"start":{"line":73,"column":1},"end":{"line":73,"column":1}},"children":[{"type":"text","value":"CESM Last Millennium simulation","position":{"start":{"line":73,"column":1},"end":{"line":73,"column":1}},"key":"wynLPMlqcG"}],"urlSource":"https://www.cesm.ucar.edu/community-projects/lme","key":"pJDTQOo4oN"},{"type":"text","value":" and proxy records stored on the ","position":{"start":{"line":73,"column":1},"end":{"line":73,"column":1}},"key":"nfNnuuFoE2"},{"type":"link","url":"https://lipdverse.org","position":{"start":{"line":73,"column":1},"end":{"line":73,"column":1}},"children":[{"type":"text","value":"LiPDverse","position":{"start":{"line":73,"column":1},"end":{"line":73,"column":1}},"key":"uowakeTIVI"}],"urlSource":"https://lipdverse.org","key":"kJD7otXNfW"},{"type":"text","value":". This repository contains paleoclimate datasets that have been curated by the community and are archived in a standard format, facilitating analysis.","position":{"start":{"line":73,"column":1},"end":{"line":73,"column":1}},"key":"iEk0c02n5Y"}],"key":"gP4fxbJKBR"},{"type":"paragraph","position":{"start":{"line":75,"column":1},"end":{"line":78,"column":1}},"children":[{"type":"strong","position":{"start":{"line":75,"column":1},"end":{"line":75,"column":1}},"children":[{"type":"text","value":"Contributors:","position":{"start":{"line":75,"column":1},"end":{"line":75,"column":1}},"key":"iAXFLE8EQh"}],"key":"zf8uzvTr6s"},{"type":"text","value":"\n","position":{"start":{"line":75,"column":1},"end":{"line":75,"column":1}},"key":"BJuvcDGd6O"},{"type":"link","url":"https://github.com/ProjectPythia/paleoPCA-Cookbook/graphs/contributors","children":[{"type":"image","url":"/build/aac7fcc7e0142c8b59d06e007eb819ab.svg","key":"rQy74zFiN8","urlSource":"https://contrib.rocks/image?repo=ProjectPythia/paleoPCA-Cookbook"}],"urlSource":"https://github.com/ProjectPythia/paleoPCA-Cookbook/graphs/contributors","error":true,"key":"MSGvGOzccm"}],"key":"p1VQIGUbUv"},{"type":"heading","depth":3,"position":{"start":{"line":80,"column":1},"end":{"line":80,"column":1}},"children":[{"type":"link","url":"https://projectpythia.org/esgf-cookbook/","position":{"start":{"line":80,"column":1},"end":{"line":80,"column":1}},"children":[{"type":"text","value":"ESGF Cookbook","position":{"start":{"line":80,"column":1},"end":{"line":80,"column":1}},"key":"zSN6M4rAib"}],"urlSource":"https://projectpythia.org/esgf-cookbook/","key":"uzkXbDOeHO"}],"identifier":"esgf-cookbook","label":"ESGF Cookbook","html_id":"esgf-cookbook","implicit":true,"key":"ZJ06YZh8nD"},{"type":"image","url":"/build/922d9950c29154f0bf3697508674d154.png","alt":"ESGF2 thumbnail","width":"250","align":"left","key":"Ane5ScOOFH","urlSource":"https://raw.githubusercontent.com/ProjectPythia/esgf-cookbook/refs/heads/main/notebooks/images/logos/esgf2-us.png?raw=true"},{"type":"paragraph","position":{"start":{"line":88,"column":1},"end":{"line":88,"column":1}},"children":[{"type":"strong","position":{"start":{"line":88,"column":1},"end":{"line":88,"column":1}},"children":[{"type":"text","value":"Authors:","position":{"start":{"line":88,"column":1},"end":{"line":88,"column":1}},"key":"OQBqqJhWXW"}],"key":"epLfW5n9p9"},{"type":"text","value":" ","position":{"start":{"line":88,"column":1},"end":{"line":88,"column":1}},"key":"n8Lgygi686"},{"type":"link","url":"@mgrover1","position":{"start":{"line":88,"column":1},"end":{"line":88,"column":1}},"children":[{"type":"text","value":"Max Grover","position":{"start":{"line":88,"column":1},"end":{"line":88,"column":1}},"key":"TiWxQTvkRF"}],"urlSource":"@mgrover1","key":"Km7ua6o1tS"},{"type":"text","value":", ","position":{"start":{"line":88,"column":1},"end":{"line":88,"column":1}},"key":"LoWZ2LqREI"},{"type":"link","url":"@nocollier","position":{"start":{"line":88,"column":1},"end":{"line":88,"column":1}},"children":[{"type":"text","value":"Nathan Collier","position":{"start":{"line":88,"column":1},"end":{"line":88,"column":1}},"key":"xBXfkhN6PF"}],"urlSource":"@nocollier","key":"HcqB7wf4tf"},{"type":"text","value":", ","position":{"start":{"line":88,"column":1},"end":{"line":88,"column":1}},"key":"i4N3rxDFvH"},{"type":"link","url":"@cehbrecht","position":{"start":{"line":88,"column":1},"end":{"line":88,"column":1}},"children":[{"type":"text","value":"Carsten Ehbrecht","position":{"start":{"line":88,"column":1},"end":{"line":88,"column":1}},"key":"QQSkNvkOzN"}],"urlSource":"@cehbrecht","key":"Bm7ztiMvXb"},{"type":"text","value":", ","position":{"start":{"line":88,"column":1},"end":{"line":88,"column":1}},"key":"CskHkJwKvY"},{"type":"link","url":"@jacnugent","position":{"start":{"line":88,"column":1},"end":{"line":88,"column":1}},"children":[{"type":"text","value":"Jacqueline Nugent","position":{"start":{"line":88,"column":1},"end":{"line":88,"column":1}},"key":"KBoNVrK5WM"}],"urlSource":"@jacnugent","key":"wgs0JT8IIk"},{"type":"text","value":", and ","position":{"start":{"line":88,"column":1},"end":{"line":88,"column":1}},"key":"LGYegxuT7k"},{"type":"link","url":"@griverat","position":{"start":{"line":88,"column":1},"end":{"line":88,"column":1}},"children":[{"type":"text","value":"Gerardo Rivera Tello","position":{"start":{"line":88,"column":1},"end":{"line":88,"column":1}},"key":"vxq7dGwM6p"}],"urlSource":"@griverat","key":"QzqkiX2mRz"}],"key":"Mdndj1FeH6"},{"type":"paragraph","position":{"start":{"line":90,"column":1},"end":{"line":90,"column":1}},"children":[{"type":"cite","url":"doi:10.5281/zenodo.11663067","position":{"start":{"line":90,"column":1},"end":{"line":90,"column":1}},"children":[{"type":"text","value":"Grover ","key":"cGk1JLXFOs"},{"type":"emphasis","children":[{"type":"text","value":"et al.","key":"FzOTURvoXS"}],"key":"qwhYmBSoME"},{"type":"text","value":" (2025)","key":"i6ryW6NhBd"}],"kind":"narrative","label":"https://doi.org/10.5281/zenodo.11663067","identifier":"doi:10.5281/zenodo.11663067","enumerator":"5","key":"P9W37QxmLd"}],"key":"ITHY4dSV45"},{"type":"paragraph","position":{"start":{"line":92,"column":1},"end":{"line":92,"column":1}},"children":[{"type":"text","value":"This Cookbook covers how to access and analyze datasets that can be accessed from Earth System Grid Federation (ESGF) cyberinfrastructure.","position":{"start":{"line":92,"column":1},"end":{"line":92,"column":1}},"key":"wcLKAnpGON"}],"key":"nIdBRtEtPl"},{"type":"paragraph","position":{"start":{"line":94,"column":1},"end":{"line":94,"column":1}},"children":[{"type":"text","value":"This cookbook focuses on highlighting analysis recipes, as well as data acccess methods, all accesible within the Python programming language. This cookbook also spans beyond the scope of a single Climate Model Intercomparison Project (ex. CMIP6), expanding to other experiments/datasets such as CMIP5 and obs4MIPs.","position":{"start":{"line":94,"column":1},"end":{"line":94,"column":1}},"key":"HbWPSIj2TO"}],"key":"qCrZOKZ5YB"},{"type":"paragraph","position":{"start":{"line":96,"column":1},"end":{"line":99,"column":1}},"children":[{"type":"strong","position":{"start":{"line":96,"column":1},"end":{"line":96,"column":1}},"children":[{"type":"text","value":"Contributors:","position":{"start":{"line":96,"column":1},"end":{"line":96,"column":1}},"key":"ucuxaT2AHJ"}],"key":"O87PPGa6rw"},{"type":"text","value":"\n","position":{"start":{"line":96,"column":1},"end":{"line":96,"column":1}},"key":"o9RKGcZfyQ"},{"type":"link","url":"https://github.com/ProjectPythia/esgf-cookbook/graphs/contributors","children":[{"type":"image","url":"/build/55899dbb61fcbe4bd01e7022edb8b7b2.svg","key":"NvS8YHjc6T","urlSource":"https://contrib.rocks/image?repo=ProjectPythia/esgf-cookbook"}],"urlSource":"https://github.com/ProjectPythia/esgf-cookbook/graphs/contributors","error":true,"key":"lwh1y5Erxx"}],"key":"ISrHpZIFaC"},{"type":"heading","depth":3,"position":{"start":{"line":101,"column":1},"end":{"line":101,"column":1}},"children":[{"type":"link","url":"https://projectpythia.org/radar-cookbook/","position":{"start":{"line":101,"column":1},"end":{"line":101,"column":1}},"children":[{"type":"text","value":"Radar Cookbook","position":{"start":{"line":101,"column":1},"end":{"line":101,"column":1}},"key":"SCuqKxHxEm"}],"urlSource":"https://projectpythia.org/radar-cookbook/","key":"KMn6pgvpjp"}],"identifier":"radar-cookbook","label":"Radar Cookbook","html_id":"radar-cookbook","implicit":true,"key":"WlEnGwHhBu"},{"type":"image","url":"/build/0855cd308edd14427c96b5f2f1ae1323.png","alt":"ARM logo","width":"300","align":"left","key":"Pb9Eg1DsAv","urlSource":"https://raw.githubusercontent.com/projectpythia/radar-cookbook/main/notebooks/images/logos/arm_logo.png"},{"type":"paragraph","position":{"start":{"line":109,"column":1},"end":{"line":109,"column":1}},"children":[{"type":"strong","position":{"start":{"line":109,"column":1},"end":{"line":109,"column":1}},"children":[{"type":"text","value":"Authors:","position":{"start":{"line":109,"column":1},"end":{"line":109,"column":1}},"key":"IMP6dmdpbx"}],"key":"qZAOITaCcS"},{"type":"text","value":" ","position":{"start":{"line":109,"column":1},"end":{"line":109,"column":1}},"key":"gEsmGDzmXv"},{"type":"link","url":"https://github.com/mgrover1","position":{"start":{"line":109,"column":1},"end":{"line":109,"column":1}},"children":[{"type":"text","value":"Max Grover","position":{"start":{"line":109,"column":1},"end":{"line":109,"column":1}},"key":"c88zAZOZvd"}],"urlSource":"https://github.com/mgrover1","error":true,"key":"U0aAVnl7T9"},{"type":"text","value":", ","position":{"start":{"line":109,"column":1},"end":{"line":109,"column":1}},"key":"bKgNHmDr1R"},{"type":"link","url":"https://github.com/zssherman","position":{"start":{"line":109,"column":1},"end":{"line":109,"column":1}},"children":[{"type":"text","value":"Zachary Sherman","position":{"start":{"line":109,"column":1},"end":{"line":109,"column":1}},"key":"gYWKckxWR7"}],"urlSource":"https://github.com/zssherman","error":true,"key":"PkBlKHbaNo"},{"type":"text","value":", ","position":{"start":{"line":109,"column":1},"end":{"line":109,"column":1}},"key":"QSXamTFWxS"},{"type":"link","url":"https://github.com/gewitterblitz","position":{"start":{"line":109,"column":1},"end":{"line":109,"column":1}},"children":[{"type":"text","value":"Milind Sharma","position":{"start":{"line":109,"column":1},"end":{"line":109,"column":1}},"key":"fKGMnmyLwx"}],"urlSource":"https://github.com/gewitterblitz","error":true,"key":"XZFauvJ21F"},{"type":"text","value":", ","position":{"start":{"line":109,"column":1},"end":{"line":109,"column":1}},"key":"cU3gKIPbRG"},{"type":"link","url":"https://github.com/aladinor","position":{"start":{"line":109,"column":1},"end":{"line":109,"column":1}},"children":[{"type":"text","value":"Alfonso Ladino","position":{"start":{"line":109,"column":1},"end":{"line":109,"column":1}},"key":"IAWDHsSjyv"}],"urlSource":"https://github.com/aladinor","error":true,"key":"OMQRlClyVY"},{"type":"text","value":", ","position":{"start":{"line":109,"column":1},"end":{"line":109,"column":1}},"key":"DOIP2wy6Fe"},{"type":"link","url":"https://github.com/crystalclearwx","position":{"start":{"line":109,"column":1},"end":{"line":109,"column":1}},"children":[{"type":"text","value":"Crystal Camron","position":{"start":{"line":109,"column":1},"end":{"line":109,"column":1}},"key":"WAhGIXtYwP"}],"urlSource":"https://github.com/crystalclearwx","error":true,"key":"qZOFDouAYU"},{"type":"text","value":", and ","position":{"start":{"line":109,"column":1},"end":{"line":109,"column":1}},"key":"JsSBVUHXAf"},{"type":"link","url":"https://github.com/TakashiUNUMA","position":{"start":{"line":109,"column":1},"end":{"line":109,"column":1}},"children":[{"type":"text","value":"Takashi Unuma","position":{"start":{"line":109,"column":1},"end":{"line":109,"column":1}},"key":"bZV7EgoidR"}],"urlSource":"https://github.com/TakashiUNUMA","error":true,"key":"kGggt8biP3"}],"key":"LaYW5rt0gC"},{"type":"paragraph","position":{"start":{"line":111,"column":1},"end":{"line":111,"column":1}},"children":[{"type":"cite","url":"doi:10.5281/zenodo.8075854","position":{"start":{"line":111,"column":1},"end":{"line":111,"column":1}},"children":[{"type":"text","value":"Grover ","key":"cAq25dYZv1"},{"type":"emphasis","children":[{"type":"text","value":"et al.","key":"TE3dYpqoXv"}],"key":"qV6zWyZpTf"},{"type":"text","value":" (2023)","key":"NhXgk928Zt"}],"kind":"narrative","label":"https://doi.org/10.5281/zenodo.8075854","identifier":"doi:10.5281/zenodo.8075854","enumerator":"6","key":"SPnXX0cQcW"}],"key":"mhTf8gZfYS"},{"type":"paragraph","position":{"start":{"line":113,"column":1},"end":{"line":113,"column":1}},"children":[{"type":"text","value":"Pythia’s very first cookbook continues to grow!","position":{"start":{"line":113,"column":1},"end":{"line":113,"column":1}},"key":"c70lvNHcOw"}],"key":"Ct6Pu8gxAE"},{"type":"paragraph","position":{"start":{"line":115,"column":1},"end":{"line":115,"column":1}},"children":[{"type":"text","value":"This cookbook provides the essential materials to learning how to work with weather radar data using Python. Most of the curriculum is focused around the Python ARM Toolkit. Once you go through this material, you will have the skills to read in radar data, apply data corrections, and visualize your data, building off of the core foundational Python material covered in the Foundations Book","position":{"start":{"line":115,"column":1},"end":{"line":115,"column":1}},"key":"grj5h9vshc"}],"key":"T2kl2nTEKb"},{"type":"paragraph","position":{"start":{"line":117,"column":1},"end":{"line":117,"column":1}},"children":[{"type":"text","value":"The Example Workflows section contains a growing collection of real-world case studies.","position":{"start":{"line":117,"column":1},"end":{"line":117,"column":1}},"key":"Ut4YV2RW4Z"}],"key":"C5uYr22xwo"},{"type":"paragraph","position":{"start":{"line":119,"column":1},"end":{"line":122,"column":1}},"children":[{"type":"strong","position":{"start":{"line":119,"column":1},"end":{"line":119,"column":1}},"children":[{"type":"text","value":"Contributors:","position":{"start":{"line":119,"column":1},"end":{"line":119,"column":1}},"key":"h6xvW9US8F"}],"key":"W1TM6SXx6k"},{"type":"text","value":"\n","position":{"start":{"line":119,"column":1},"end":{"line":119,"column":1}},"key":"wFuI4SoKcl"},{"type":"link","url":"https://github.com/ProjectPythia/radar-cookbook/graphs/contributors","children":[{"type":"image","url":"/build/1bd1dcd0cfe77c52146f5d9c6bf39ecc.svg","key":"xQOeo0zU8K","urlSource":"https://contrib.rocks/image?repo=ProjectPythia/radar-cookbook"}],"urlSource":"https://github.com/ProjectPythia/radar-cookbook/graphs/contributors","error":true,"key":"BNtMza6pAp"}],"key":"IWI8Cs5ESR"},{"type":"heading","depth":3,"position":{"start":{"line":124,"column":1},"end":{"line":124,"column":1}},"children":[{"type":"link","url":"https://projectpythia.org/ERA5_interactive-cookbook/","position":{"start":{"line":124,"column":1},"end":{"line":124,"column":1}},"children":[{"type":"text","value":"ARCO ERA-5 Interactive Visualization Cookbook","position":{"start":{"line":124,"column":1},"end":{"line":124,"column":1}},"key":"XIBgHHzsvX"}],"urlSource":"https://projectpythia.org/ERA5_interactive-cookbook/","key":"IwRern6Nvz"}],"identifier":"arco-era-5-interactive-visualization-cookbook","label":"ARCO ERA-5 Interactive Visualization Cookbook","html_id":"arco-era-5-interactive-visualization-cookbook","implicit":true,"key":"sD0a7foeqm"},{"type":"image","url":"/build/1825ec223fcb6dab100769cfa657e340.png","alt":"ERA5 thumbnail","width":"300","align":"center","key":"y5aYkcjiLo","urlSource":"https://raw.githubusercontent.com/ProjectPythia/ERA5_interactive-cookbook/main/thumbnail.png"},{"type":"paragraph","position":{"start":{"line":131,"column":1},"end":{"line":131,"column":1}},"children":[{"type":"strong","position":{"start":{"line":131,"column":1},"end":{"line":131,"column":1}},"children":[{"type":"text","value":"Authors:","position":{"start":{"line":131,"column":1},"end":{"line":131,"column":1}},"key":"rnOUzx56TA"}],"key":"Shp00fgTTh"},{"type":"text","value":" ","position":{"start":{"line":131,"column":1},"end":{"line":131,"column":1}},"key":"JvxlQTdCNX"},{"type":"link","url":"https://github.com/ktyle","position":{"start":{"line":131,"column":1},"end":{"line":131,"column":1}},"children":[{"type":"text","value":"Kevin Tyle","position":{"start":{"line":131,"column":1},"end":{"line":131,"column":1}},"key":"mRc8naeC7L"}],"urlSource":"https://github.com/ktyle","error":true,"key":"KiCGc3Y8qW"},{"type":"text","value":", ","position":{"start":{"line":131,"column":1},"end":{"line":131,"column":1}},"key":"UbUjvcxWyH"},{"type":"link","url":"https://github.com/Michael-Barletta","position":{"start":{"line":131,"column":1},"end":{"line":131,"column":1}},"children":[{"type":"text","value":"Michael Barletta","position":{"start":{"line":131,"column":1},"end":{"line":131,"column":1}},"key":"IXXQwofAFq"}],"urlSource":"https://github.com/Michael-Barletta","error":true,"key":"ME2O0pTqOx"},{"type":"text","value":", ","position":{"start":{"line":131,"column":1},"end":{"line":131,"column":1}},"key":"pdtWLHP8cJ"},{"type":"link","url":"https://github.com/negin513","position":{"start":{"line":131,"column":1},"end":{"line":131,"column":1}},"children":[{"type":"text","value":"Negin Sobhani","position":{"start":{"line":131,"column":1},"end":{"line":131,"column":1}},"key":"LNUvcChg2u"}],"urlSource":"https://github.com/negin513","error":true,"key":"KDjZ67l3d1"},{"type":"text","value":", ","position":{"start":{"line":131,"column":1},"end":{"line":131,"column":1}},"key":"bjbb8qjUDd"},{"type":"link","url":"https://github.com/ncote","position":{"start":{"line":131,"column":1},"end":{"line":131,"column":1}},"children":[{"type":"text","value":"Nicholas Cote","position":{"start":{"line":131,"column":1},"end":{"line":131,"column":1}},"key":"WVIssds7Yh"}],"urlSource":"https://github.com/ncote","error":true,"key":"DXt8hUrNeX"},{"type":"text","value":" , ","position":{"start":{"line":131,"column":1},"end":{"line":131,"column":1}},"key":"z1TooS6V9c"},{"type":"link","url":"https://github.com/hrhampapura","position":{"start":{"line":131,"column":1},"end":{"line":131,"column":1}},"children":[{"type":"text","value":"Harsha Hampapura","position":{"start":{"line":131,"column":1},"end":{"line":131,"column":1}},"key":"AR3VBgU9vi"}],"urlSource":"https://github.com/hrhampapura","error":true,"key":"F8DxQacwWi"},{"type":"text","value":" , and ","position":{"start":{"line":131,"column":1},"end":{"line":131,"column":1}},"key":"F7b2g2vA6x"},{"type":"link","url":"https://github.com/philip2c","position":{"start":{"line":131,"column":1},"end":{"line":131,"column":1}},"children":[{"type":"text","value":"Philip Chmielowiec","position":{"start":{"line":131,"column":1},"end":{"line":131,"column":1}},"key":"aZCqw40yHN"}],"urlSource":"https://github.com/philip2c","error":true,"key":"GhOTBHqjUY"}],"key":"bsRln46Mbd"},{"type":"paragraph","position":{"start":{"line":133,"column":1},"end":{"line":133,"column":1}},"children":[{"type":"cite","url":"doi:10.5281/zenodo.10303236","position":{"start":{"line":133,"column":1},"end":{"line":133,"column":1}},"children":[{"type":"text","value":"Tyle ","key":"z8TnSPSXAr"},{"type":"emphasis","children":[{"type":"text","value":"et al.","key":"p0yIpFhYlU"}],"key":"A2WiJSzIwA"},{"type":"text","value":" (2023)","key":"vpnzj9o52J"}],"kind":"narrative","label":"https://doi.org/10.5281/zenodo.10303236","identifier":"doi:10.5281/zenodo.10303236","enumerator":"7","key":"c4UNPqocW7"}],"key":"QjTrf0oJV9"},{"type":"paragraph","position":{"start":{"line":135,"column":1},"end":{"line":135,"column":1}},"children":[{"type":"text","value":"This Cookbook covers accessing, regridding, and visualizing the ","position":{"start":{"line":135,"column":1},"end":{"line":135,"column":1}},"key":"yhC8rWlWYs"},{"type":"link","url":"https://www.ecmwf.int/en/forecasts/dataset/ecmwf-reanalysis-v5","position":{"start":{"line":135,"column":1},"end":{"line":135,"column":1}},"children":[{"type":"text","value":"ECMWF Reanalysis version 5","position":{"start":{"line":135,"column":1},"end":{"line":135,"column":1}},"key":"i2P9CBQsjS"}],"urlSource":"https://www.ecmwf.int/en/forecasts/dataset/ecmwf-reanalysis-v5","key":"YdNopxXzZu"},{"type":"text","value":" (aka ","position":{"start":{"line":135,"column":1},"end":{"line":135,"column":1}},"key":"V8T0R8EnQN"},{"type":"strong","position":{"start":{"line":135,"column":1},"end":{"line":135,"column":1}},"children":[{"type":"text","value":"ERA-5","position":{"start":{"line":135,"column":1},"end":{"line":135,"column":1}},"key":"xPxD5jP6bU"}],"key":"X5rvwF7k9u"},{"type":"text","value":") dataset in a ","position":{"start":{"line":135,"column":1},"end":{"line":135,"column":1}},"key":"js0p1BRcwG"},{"type":"cite","url":"https://www.frontiersin.org/articles/10.3389/fclim.2021.782909/full","position":{"start":{"line":135,"column":1},"end":{"line":135,"column":1}},"children":[{"type":"text","value":"Analysis Ready, Cloud Optimized","position":{"start":{"line":135,"column":1},"end":{"line":135,"column":1}},"key":"wcHvHyQGdn"}],"kind":"narrative","label":"Stern_2022","identifier":"https://www.frontiersin.org/articles/10.3389/fclim.2021.782909/full","enumerator":"8","key":"b719cT5C8u"},{"type":"text","value":" (aka ","position":{"start":{"line":135,"column":1},"end":{"line":135,"column":1}},"key":"ZDZfhkPpIe"},{"type":"strong","position":{"start":{"line":135,"column":1},"end":{"line":135,"column":1}},"children":[{"type":"text","value":"ARCO","position":{"start":{"line":135,"column":1},"end":{"line":135,"column":1}},"key":"Wcn1k5SbD9"}],"key":"ZGL1D8olLI"},{"type":"text","value":") format.","position":{"start":{"line":135,"column":1},"end":{"line":135,"column":1}},"key":"fblOlQ2yot"}],"key":"ukNf2QJAv6"},{"type":"paragraph","position":{"start":{"line":137,"column":1},"end":{"line":137,"column":1}},"children":[{"type":"text","value":"The ERA-5 represents the current state-of-the-art meteorological reanalysis, extending from well back into the 20th century to the present. While the data is freely-available for download by archival centers such as ","position":{"start":{"line":137,"column":1},"end":{"line":137,"column":1}},"key":"IxrafQSPas"},{"type":"link","url":"https://www.copernicus.eu/en","position":{"start":{"line":137,"column":1},"end":{"line":137,"column":1}},"children":[{"type":"text","value":"Copernicus","position":{"start":{"line":137,"column":1},"end":{"line":137,"column":1}},"key":"wb5TrfxSBg"}],"urlSource":"https://www.copernicus.eu/en","key":"dMh3PCzHIH"},{"type":"text","value":" and ","position":{"start":{"line":137,"column":1},"end":{"line":137,"column":1}},"key":"fkGoLcEyFA"},{"type":"link","url":"https://rda.ucar.edu/","position":{"start":{"line":137,"column":1},"end":{"line":137,"column":1}},"children":[{"type":"text","value":"RDA","position":{"start":{"line":137,"column":1},"end":{"line":137,"column":1}},"key":"FQi7UEftMS"}],"urlSource":"https://rda.ucar.edu/","key":"XuMsuvsbBZ"},{"type":"text","value":", the data format and directory structure are typically not well-suited for interactive exploration. Specifically, parameters of interest are stored in individual files, for a limited period of time.","position":{"start":{"line":137,"column":1},"end":{"line":137,"column":1}},"key":"Ht2iEeQcNy"}],"key":"RQ3FNvPb0p"},{"type":"paragraph","position":{"start":{"line":139,"column":1},"end":{"line":139,"column":1}},"children":[{"type":"text","value":"A team at Google Cloud and Research has made interactive exploration much more tenable by representing the data in ","position":{"start":{"line":139,"column":1},"end":{"line":139,"column":1}},"key":"FARF82hlnM"},{"type":"link","url":"https://zarr.readthedocs.io/en/stable/","position":{"start":{"line":139,"column":1},"end":{"line":139,"column":1}},"children":[{"type":"text","value":"Zarr","position":{"start":{"line":139,"column":1},"end":{"line":139,"column":1}},"key":"cfBUrVIUSv"}],"urlSource":"https://zarr.readthedocs.io/en/stable/","key":"je094gEjNP"},{"type":"text","value":" format.","position":{"start":{"line":139,"column":1},"end":{"line":139,"column":1}},"key":"gNR6EQOrgb"}],"key":"QtbkcrtNdU"},{"type":"paragraph","position":{"start":{"line":141,"column":1},"end":{"line":141,"column":1}},"children":[{"type":"text","value":"This Cookbook demonstrates how to do the following:","position":{"start":{"line":141,"column":1},"end":{"line":141,"column":1}},"key":"Vgl8Ec2KeH"}],"key":"UI0KMzdEGX"},{"type":"list","ordered":true,"start":1,"spread":false,"position":{"start":{"line":143,"column":1},"end":{"line":147,"column":1}},"children":[{"type":"listItem","spread":true,"position":{"start":{"line":143,"column":1},"end":{"line":143,"column":1}},"children":[{"type":"text","value":"Access parameters of interest from the Zarr store on Google Cloud","position":{"start":{"line":143,"column":1},"end":{"line":143,"column":1}},"key":"eBqVdTrF6p"}],"key":"qkOG9LV93G"},{"type":"listItem","spread":true,"position":{"start":{"line":144,"column":1},"end":{"line":144,"column":1}},"children":[{"type":"text","value":"Regrid from model native (Gaussian) to lat-lon (Cartesian) coordinates","position":{"start":{"line":144,"column":1},"end":{"line":144,"column":1}},"key":"xctc5kZk96"}],"key":"eTpDckz62t"},{"type":"listItem","spread":true,"position":{"start":{"line":145,"column":1},"end":{"line":145,"column":1}},"children":[{"type":"text","value":"Plot a map at a specific time using Matplotlib and Cartopy","position":{"start":{"line":145,"column":1},"end":{"line":145,"column":1}},"key":"EY7BO9lMJn"}],"key":"kvAA18bdFy"},{"type":"listItem","spread":true,"position":{"start":{"line":146,"column":1},"end":{"line":147,"column":1}},"children":[{"type":"text","value":"Create interactive visualizations, leveraging the ","position":{"start":{"line":146,"column":1},"end":{"line":146,"column":1}},"key":"Vuc0g56Rvp"},{"type":"link","url":"https://holoviz.org","position":{"start":{"line":146,"column":1},"end":{"line":146,"column":1}},"children":[{"type":"text","value":"Holoviz","position":{"start":{"line":146,"column":1},"end":{"line":146,"column":1}},"key":"UUHWHhb4sp"}],"urlSource":"https://holoviz.org","key":"vAvCTHxDam"},{"type":"text","value":" ecosystem","position":{"start":{"line":146,"column":1},"end":{"line":146,"column":1}},"key":"t6SUjmwcy3"}],"key":"lmjtfQ2W2m"}],"key":"K7aGioqZai"},{"type":"paragraph","position":{"start":{"line":148,"column":1},"end":{"line":151,"column":1}},"children":[{"type":"strong","position":{"start":{"line":148,"column":1},"end":{"line":148,"column":1}},"children":[{"type":"text","value":"Contributors:","position":{"start":{"line":148,"column":1},"end":{"line":148,"column":1}},"key":"xZht6z4HRT"}],"key":"zxwpkTjgY7"},{"type":"text","value":"\n","position":{"start":{"line":148,"column":1},"end":{"line":148,"column":1}},"key":"wtvszetAPt"},{"type":"link","url":"https://github.com/ProjectPythia/ERA5_interactive-cookbook/graphs/contributors","children":[{"type":"image","url":"/build/ab3c3f60dea1644131c18b955a01d947.svg","key":"Srulld54cC","urlSource":"https://contrib.rocks/image?repo=ProjectPythia/ERA5_interactive-cookbook"}],"urlSource":"https://github.com/ProjectPythia/ERA5_interactive-cookbook/graphs/contributors","error":true,"key":"DprmGGxkZC"}],"key":"Qn88PxU4zc"},{"type":"heading","depth":3,"position":{"start":{"line":153,"column":1},"end":{"line":153,"column":1}},"children":[{"type":"link","url":"https://projectpythia.org/wavelet-cookbook/","position":{"start":{"line":153,"column":1},"end":{"line":153,"column":1}},"children":[{"type":"text","value":"Wavelet Cookbook","position":{"start":{"line":153,"column":1},"end":{"line":153,"column":1}},"key":"A3z37dHfx1"}],"urlSource":"https://projectpythia.org/wavelet-cookbook/","key":"bEGihj0K3F"}],"identifier":"wavelet-cookbook","label":"Wavelet Cookbook","html_id":"wavelet-cookbook","implicit":true,"key":"Gh1FvERfOh"},{"type":"image","url":"/build/bcb01b387403102140345f8aba643fec.png","alt":"Wavelet thumbnail","width":"300","align":"left","key":"SQoBMstTsV","urlSource":"https://raw.githubusercontent.com/ProjectPythia/wavelet-cookbook/main/thumbnail.png"},{"type":"paragraph","position":{"start":{"line":161,"column":1},"end":{"line":161,"column":1}},"children":[{"type":"strong","position":{"start":{"line":161,"column":1},"end":{"line":161,"column":1}},"children":[{"type":"text","value":"Authors:","position":{"start":{"line":161,"column":1},"end":{"line":161,"column":1}},"key":"h9CgyswFoa"}],"key":"FHvpEMpetT"},{"type":"text","value":" ","position":{"start":{"line":161,"column":1},"end":{"line":161,"column":1}},"key":"FmwMtJWQC0"},{"type":"link","url":"https://github.com/cyschneck","position":{"start":{"line":161,"column":1},"end":{"line":161,"column":1}},"children":[{"type":"text","value":"Cora Schneck","position":{"start":{"line":161,"column":1},"end":{"line":161,"column":1}},"key":"QiaOsG2JWc"}],"urlSource":"https://github.com/cyschneck","error":true,"key":"Gi7Vne3oTH"}],"key":"cvaFYmRSXl"},{"type":"paragraph","position":{"start":{"line":163,"column":1},"end":{"line":163,"column":1}},"children":[{"type":"cite","url":"doi:10.5281/zenodo.14550038","position":{"start":{"line":163,"column":1},"end":{"line":163,"column":1}},"children":[{"type":"text","value":"Schneck & Wavelet Cookbook contributors (2025)","key":"t6ziX5gr6J"}],"kind":"narrative","label":"https://doi.org/10.5281/zenodo.14550038","identifier":"doi:10.5281/zenodo.14550038","enumerator":"9","key":"SxYiQCQTMr"}],"key":"qOEX6scArD"},{"type":"paragraph","position":{"start":{"line":165,"column":1},"end":{"line":165,"column":1}},"children":[{"type":"text","value":"This Cookbook covers how to work with wavelets in Python. Wavelets are a powerful tool to analyze time-series data. When data frequencies vary over time, wavelets can be applied to analysis trends and overcome the time/frequency limitations of Fourier Transforms","position":{"start":{"line":165,"column":1},"end":{"line":165,"column":1}},"key":"jTxs410HuK"}],"key":"fVcQWtlp9f"},{"type":"paragraph","position":{"start":{"line":167,"column":1},"end":{"line":170,"column":1}},"children":[{"type":"strong","position":{"start":{"line":167,"column":1},"end":{"line":167,"column":1}},"children":[{"type":"text","value":"Contributors:","position":{"start":{"line":167,"column":1},"end":{"line":167,"column":1}},"key":"GLGSeKfcTB"}],"key":"tPGURXNvVM"},{"type":"text","value":"\n","position":{"start":{"line":167,"column":1},"end":{"line":167,"column":1}},"key":"npQj3CxYWQ"},{"type":"link","url":"https://github.com/ProjectPythia/wavelet-cookbook/graphs/contributors","children":[{"type":"image","url":"/build/3bb0f103e9077a8008c2d7f2f8c3d5b9.svg","key":"gSwq02A8UC","urlSource":"https://contrib.rocks/image?repo=ProjectPythia/wavelet-cookbook"}],"urlSource":"https://github.com/ProjectPythia/wavelet-cookbook/graphs/contributors","error":true,"key":"wAHa2a0mW4"}],"key":"s5pYN3fWRV"},{"type":"heading","depth":2,"position":{"start":{"line":172,"column":1},"end":{"line":172,"column":1}},"children":[{"type":"text","value":"The 2024 Cook-off","position":{"start":{"line":172,"column":1},"end":{"line":172,"column":1}},"key":"S2PE6JKqr1"}],"identifier":"the-2024-cook-off","label":"The 2024 Cook-off","html_id":"the-2024-cook-off","implicit":true,"key":"Fsf4quR82K"},{"type":"heading","depth":3,"position":{"start":{"line":174,"column":1},"end":{"line":174,"column":1}},"children":[{"type":"text","value":"In pictures","position":{"start":{"line":174,"column":1},"end":{"line":174,"column":1}},"key":"cJfFns5NfN"}],"identifier":"in-pictures","label":"In pictures","html_id":"in-pictures","implicit":true,"key":"ITu0LcGbih"},{"type":"paragraph","children":[{"type":"image","url":"/build/IMG_5686-637e7e46a9f2a89cf5452abd783aa892.jpeg","alt":"2024 Cookoff group photo","width":900,"key":"fbRoKTR4G7","urlSource":"../../_static/images/posts/IMG_5686.jpeg"}],"key":"brr7H4O4XS"},{"type":"break","key":"J8gO9CxwSO"},{"type":"paragraph","children":[{"type":"image","url":"/build/IMG_5854-71df9ffe57e4d6600aa3ee859980b5f6.jpeg","alt":"Breakout group","width":250,"key":"Cg5LwPzqJ7","urlSource":"../../_static/images/posts/IMG_5854.jpeg"},{"type":"text","value":" ","key":"rxkiiCEApw"},{"type":"image","url":"/build/IMG_6546-5b54fdb85de4672b9beabc9040eb46ae.jpg","alt":"Cookoff attendees at Mesa Lab","width":250,"key":"QSs2a2vTMN","urlSource":"../../_static/images/posts/IMG_6546.jpg"},{"type":"text","value":" ","key":"yIK2kD5ueh"},{"type":"image","url":"/build/IMG_6055-7694a5f7c1ecec7447564d2914b1aa97.jpeg","alt":"Virtual presentation","width":250,"key":"kdURJEIneb","urlSource":"../../_static/images/posts/IMG_6055.jpeg"}],"key":"o3UqDs3wpk"},{"type":"heading","depth":3,"position":{"start":{"line":182,"column":1},"end":{"line":182,"column":1}},"children":[{"type":"text","value":"By the numbers","position":{"start":{"line":182,"column":1},"end":{"line":182,"column":1}},"key":"dY85xiiy0l"}],"identifier":"by-the-numbers","label":"By the numbers","html_id":"by-the-numbers","implicit":true,"key":"UjEB1Z0zxw"},{"type":"list","ordered":false,"spread":false,"position":{"start":{"line":184,"column":1},"end":{"line":198,"column":1}},"children":[{"type":"listItem","spread":true,"position":{"start":{"line":184,"column":1},"end":{"line":184,"column":1}},"children":[{"type":"text","value":"Number of attendees: 92 (49 in-person, 43 remote)","position":{"start":{"line":184,"column":1},"end":{"line":184,"column":1}},"key":"GMCFa8GHb1"}],"key":"ifxQn4yN9D"},{"type":"listItem","spread":true,"position":{"start":{"line":185,"column":1},"end":{"line":185,"column":1}},"children":[{"type":"text","value":"Number of attendees receiving travel support from Project Pythia: 16","position":{"start":{"line":185,"column":1},"end":{"line":185,"column":1}},"key":"KHNnlEY2p3"}],"key":"GMom5y4Gdf"},{"type":"listItem","spread":true,"position":{"start":{"line":186,"column":1},"end":{"line":190,"column":1}},"children":[{"type":"text","value":"Career stage:","position":{"start":{"line":186,"column":1},"end":{"line":186,"column":1}},"key":"aGx8hhhdPq"},{"type":"list","ordered":false,"spread":false,"position":{"start":{"line":187,"column":1},"end":{"line":190,"column":1}},"children":[{"type":"listItem","spread":true,"position":{"start":{"line":187,"column":1},"end":{"line":187,"column":1}},"children":[{"type":"text","value":"14% undergrad","position":{"start":{"line":187,"column":1},"end":{"line":187,"column":1}},"key":"Ut5UPKKjXU"}],"key":"AUQfFoFJkJ"},{"type":"listItem","spread":true,"position":{"start":{"line":188,"column":1},"end":{"line":188,"column":1}},"children":[{"type":"text","value":"29% graduate","position":{"start":{"line":188,"column":1},"end":{"line":188,"column":1}},"key":"yRSoGUJXfm"}],"key":"TFSY3ZKPSp"},{"type":"listItem","spread":true,"position":{"start":{"line":189,"column":1},"end":{"line":189,"column":1}},"children":[{"type":"text","value":"14% postdoc","position":{"start":{"line":189,"column":1},"end":{"line":189,"column":1}},"key":"nXBF72zJkI"}],"key":"zrnOUyVbTf"},{"type":"listItem","spread":true,"position":{"start":{"line":190,"column":1},"end":{"line":190,"column":1}},"children":[{"type":"text","value":"43% faculty or staff","position":{"start":{"line":190,"column":1},"end":{"line":190,"column":1}},"key":"EauCC8JT0N"}],"key":"Q8WLUfAONt"}],"key":"vA9rDzdZVc"}],"key":"F0hiQyRKzw"},{"type":"listItem","spread":true,"position":{"start":{"line":191,"column":1},"end":{"line":194,"column":1}},"children":[{"type":"text","value":"Gender of attendees:","position":{"start":{"line":191,"column":1},"end":{"line":191,"column":1}},"key":"ytzTne1u8F"},{"type":"list","ordered":false,"spread":false,"position":{"start":{"line":192,"column":1},"end":{"line":194,"column":1}},"children":[{"type":"listItem","spread":true,"position":{"start":{"line":192,"column":1},"end":{"line":192,"column":1}},"children":[{"type":"text","value":"59% men","position":{"start":{"line":192,"column":1},"end":{"line":192,"column":1}},"key":"swngBalN1X"}],"key":"UJkEh8jCYI"},{"type":"listItem","spread":true,"position":{"start":{"line":193,"column":1},"end":{"line":193,"column":1}},"children":[{"type":"text","value":"30% women","position":{"start":{"line":193,"column":1},"end":{"line":193,"column":1}},"key":"fH25e4VX0j"}],"key":"uchPPVm758"},{"type":"listItem","spread":true,"position":{"start":{"line":194,"column":1},"end":{"line":194,"column":1}},"children":[{"type":"text","value":"11% other","position":{"start":{"line":194,"column":1},"end":{"line":194,"column":1}},"key":"MhtXWGTC9Q"}],"key":"QhMHNoeGKo"}],"key":"gs896Q6I9S"}],"key":"mRw9OxvyPs"},{"type":"listItem","spread":true,"position":{"start":{"line":195,"column":1},"end":{"line":195,"column":1}},"children":[{"type":"text","value":"Number of individual project breakout groups: 9","position":{"start":{"line":195,"column":1},"end":{"line":195,"column":1}},"key":"qsGbj85LQw"}],"key":"oeDuvV8x9T"},{"type":"listItem","spread":true,"position":{"start":{"line":196,"column":1},"end":{"line":196,"column":1}},"children":[{"type":"text","value":"New cookbooks published to the ","position":{"start":{"line":196,"column":1},"end":{"line":196,"column":1}},"key":"RvqC8UcfrX"},{"type":"link","url":"https://cookbooks.projectpythia.org","position":{"start":{"line":196,"column":1},"end":{"line":196,"column":1}},"children":[{"type":"text","value":"Pythia Gallery","position":{"start":{"line":196,"column":1},"end":{"line":196,"column":1}},"key":"q7LUslh9Fc"}],"urlSource":"https://cookbooks.projectpythia.org","key":"mI83mCd5Qr"},{"type":"text","value":": 5 ","position":{"start":{"line":196,"column":1},"end":{"line":196,"column":1}},"key":"T4iijSv8zm"},{"type":"emphasis","position":{"start":{"line":196,"column":1},"end":{"line":196,"column":1}},"children":[{"type":"text","value":"(as of this writing)","position":{"start":{"line":196,"column":1},"end":{"line":196,"column":1}},"key":"L6TxeyArAl"}],"key":"dg4LNVSews"}],"key":"GLXK9th2OE"},{"type":"listItem","spread":true,"position":{"start":{"line":197,"column":1},"end":{"line":198,"column":1}},"children":[{"type":"text","value":"Heavily revised cookbooks: 2","position":{"start":{"line":197,"column":1},"end":{"line":197,"column":1}},"key":"ws2nXBQlnC"}],"key":"PpJTKLglQA"}],"key":"SsBxLNUTt8"},{"type":"heading","depth":2,"position":{"start":{"line":199,"column":1},"end":{"line":199,"column":1}},"children":[{"type":"text","value":"Want to get involved?","position":{"start":{"line":199,"column":1},"end":{"line":199,"column":1}},"key":"DGQa6k9pTU"}],"identifier":"want-to-get-involved","label":"Want to get involved?","html_id":"want-to-get-involved","implicit":true,"key":"nWKmQdVuyl"},{"type":"link","class":"btn btn-light btn-lg","style":{"display":"flex","alignItems":"center","fontWeight":"600","textDecoration":"none"},"url":"","children":[{"type":"text","value":"SAVE THE DATE! Project Pythia is hosting our next Cookbook Cook-off hackathon event at the NSF NCAR's Mesa Lab, August 5-8 2025.","key":"BdfdnvjRMX"}],"urlSource":"","key":"rW3UstwC8t"},{"type":"paragraph","position":{"start":{"line":205,"column":1},"end":{"line":205,"column":1}},"children":[{"type":"text","value":"Do you have some feedback or ideaa for a new Cookbook project? Unsure how to get started? We’d love to hear from you at any of our ","position":{"start":{"line":205,"column":1},"end":{"line":205,"column":1}},"key":"xIfYsbmtNP"},{"type":"link","url":"https://projectpythia.org/#monthly-pythia-meetings","position":{"start":{"line":205,"column":1},"end":{"line":205,"column":1}},"children":[{"type":"text","value":"open meetings","position":{"start":{"line":205,"column":1},"end":{"line":205,"column":1}},"key":"PIH0GTt5qb"}],"urlSource":"https://projectpythia.org/#monthly-pythia-meetings","key":"lNOiJ5Yg3l"},{"type":"text","value":", through the ","position":{"start":{"line":205,"column":1},"end":{"line":205,"column":1}},"key":"HNVOxzZNaO"},{"type":"link","url":"https://discourse.pangeo.io/c/education/project-pythia/","position":{"start":{"line":205,"column":1},"end":{"line":205,"column":1}},"children":[{"type":"text","value":"Pangeo Discourse","position":{"start":{"line":205,"column":1},"end":{"line":205,"column":1}},"key":"xxK5IMKvdY"}],"urlSource":"https://discourse.pangeo.io/c/education/project-pythia/","key":"KeWPsejVNN"},{"type":"text","value":", or via any of our social media. Join us at our next Cook-off 2025!","position":{"start":{"line":205,"column":1},"end":{"line":205,"column":1}},"key":"LYwiVgAgvm"}],"key":"aXiWd8Hy4S"},{"type":"paragraph","position":{"start":{"line":207,"column":1},"end":{"line":207,"column":1}},"children":[{"type":"text","value":"Take a look at our ","position":{"start":{"line":207,"column":1},"end":{"line":207,"column":1}},"key":"uTgjY4zUsl"},{"type":"link","url":"https://projectpythia.org/cookbook-guide","position":{"start":{"line":207,"column":1},"end":{"line":207,"column":1}},"children":[{"type":"text","value":"guide for Cookbook contributors","position":{"start":{"line":207,"column":1},"end":{"line":207,"column":1}},"key":"rtHv0xotjx"}],"urlSource":"https://projectpythia.org/cookbook-guide","key":"qULrfiLmaG"},{"type":"text","value":".","position":{"start":{"line":207,"column":1},"end":{"line":207,"column":1}},"key":"Z1XCKZWH45"}],"key":"HL8SYNNZg4"}],"key":"RzegDfrOGO"}],"key":"QSrATwokBH"},"references":{"cite":{"order":["https://doi.org/10.5281/zenodo.10909812","https://doi.org/10.5281/zenodo.12557198","https://doi.org/10.5281/zenodo.11659789","Steinman_2022","https://doi.org/10.5281/zenodo.11663067","https://doi.org/10.5281/zenodo.8075854","https://doi.org/10.5281/zenodo.10303236","Stern_2022","https://doi.org/10.5281/zenodo.14550038"],"data":{"https://doi.org/10.5281/zenodo.10909812":{"label":"https://doi.org/10.5281/zenodo.10909812","enumerator":"1","doi":"10.5281/ZENODO.10909812","html":"Ford, R. R., & EOFs Cookbook contributors. (2025). <i>EOFs Cookbook</i>. Zenodo. <a target=\"_blank\" rel=\"noreferrer\" href=\"https://doi.org/10.5281/ZENODO.10909812\">10.5281/ZENODO.10909812</a>","url":"https://doi.org/10.5281/ZENODO.10909812"},"https://doi.org/10.5281/zenodo.12557198":{"label":"https://doi.org/10.5281/zenodo.12557198","enumerator":"2","doi":"10.5281/ZENODO.12557198","html":"Romashkov, L., Krumhardt, K., & Ocean Biogeochemistry Cookbook Contributors. (2024). <i>Ocean Biogeochemistry Cookbook</i>. Zenodo. <a target=\"_blank\" rel=\"noreferrer\" href=\"https://doi.org/10.5281/ZENODO.12557198\">10.5281/ZENODO.12557198</a>","url":"https://doi.org/10.5281/ZENODO.12557198"},"https://doi.org/10.5281/zenodo.11659789":{"label":"https://doi.org/10.5281/zenodo.11659789","enumerator":"3","doi":"10.5281/ZENODO.11659789","html":"Khider, D., Sundar, S., & Ratnakar, V. (2024). <i>Investigating interhemispheric precipitation changes over the past millennium</i>. Zenodo. <a target=\"_blank\" rel=\"noreferrer\" href=\"https://doi.org/10.5281/ZENODO.11659789\">10.5281/ZENODO.11659789</a>","url":"https://doi.org/10.5281/ZENODO.11659789"},"Steinman_2022":{"label":"Steinman_2022","enumerator":"4","doi":"10.1073/pnas.2120015119","html":"Steinman, B. A., Stansell, N. D., Mann, M. E., Cooke, C. A., Abbott, M. B., Vuille, M., Bird, B. W., Lachniet, M. S., & Fernandez, A. (2022). Interhemispheric antiphasing of neotropical precipitation during the past millennium. <i>Proceedings of the National Academy of Sciences</i>, <i>119</i>(17). <a target=\"_blank\" rel=\"noreferrer\" href=\"https://doi.org/10.1073/pnas.2120015119\">10.1073/pnas.2120015119</a>","url":"https://doi.org/10.1073/pnas.2120015119"},"https://doi.org/10.5281/zenodo.11663067":{"label":"https://doi.org/10.5281/zenodo.11663067","enumerator":"5","doi":"10.5281/ZENODO.11663067","html":"Grover, M. A., Collier, N., Ehbrecht, C., Nugent, J., & Rivera Tello, G. A. (2025). <i>ESGF Cookbook</i>. Zenodo. <a target=\"_blank\" rel=\"noreferrer\" href=\"https://doi.org/10.5281/ZENODO.11663067\">10.5281/ZENODO.11663067</a>","url":"https://doi.org/10.5281/ZENODO.11663067"},"https://doi.org/10.5281/zenodo.8075854":{"label":"https://doi.org/10.5281/zenodo.8075854","enumerator":"6","doi":"10.5281/ZENODO.8075854","html":"Grover, M., Sherman, Z., Sharma, M., Ladino, A., Camron, C., & Radar Cookbook Contributors. (2023). <i>Radar Cookbook</i>. Zenodo. <a target=\"_blank\" rel=\"noreferrer\" href=\"https://doi.org/10.5281/ZENODO.8075854\">10.5281/ZENODO.8075854</a>","url":"https://doi.org/10.5281/ZENODO.8075854"},"https://doi.org/10.5281/zenodo.10303236":{"label":"https://doi.org/10.5281/zenodo.10303236","enumerator":"7","doi":"10.5281/ZENODO.10303236","html":"Tyle, K., Barletta, M., & ARCO ERA-5 Cookbook contributors. (2023). <i>ARCO ERA-5 Interactive Visualization Cookbook</i>. Zenodo. <a target=\"_blank\" rel=\"noreferrer\" href=\"https://doi.org/10.5281/ZENODO.10303236\">10.5281/ZENODO.10303236</a>","url":"https://doi.org/10.5281/ZENODO.10303236"},"Stern_2022":{"label":"Stern_2022","enumerator":"8","doi":"10.3389/fclim.2021.782909","html":"Stern, C., Abernathey, R., Hamman, J., Wegener, R., Lepore, C., Harkins, S., & Merose, A. (2022). Pangeo Forge: Crowdsourcing Analysis-Ready, Cloud Optimized Data Production. <i>Frontiers in Climate</i>, <i>3</i>. <a target=\"_blank\" rel=\"noreferrer\" href=\"https://doi.org/10.3389/fclim.2021.782909\">10.3389/fclim.2021.782909</a>","url":"https://doi.org/10.3389/fclim.2021.782909"},"https://doi.org/10.5281/zenodo.14550038":{"label":"https://doi.org/10.5281/zenodo.14550038","enumerator":"9","doi":"10.5281/ZENODO.14550038","html":"Schneck, C., & Wavelet Cookbook contributors. (2025). <i>Wavelet Cookbook</i>. Zenodo. <a target=\"_blank\" rel=\"noreferrer\" href=\"https://doi.org/10.5281/ZENODO.14550038\">10.5281/ZENODO.14550038</a>","url":"https://doi.org/10.5281/ZENODO.14550038"}}}},"footer":{"navigation":{"prev":{"title":"binder.projectpythia.org Maintenance","url":"/posts/2025/binderhub-status","group":"2025"},"next":{"title":"Website is live for the 2024 Cook-off hackathon","url":"/posts/2024/cookoff2024-website","group":"2024"}}},"domain":"http://localhost:3000"}