{"version":3,"kind":"Article","sha256":"aa8c7e289339a81f8ccf8dabe70a9d23723c40d5c24e71e951267d0c37a3732a","slug":"about","location":"/about.md","dependencies":[],"frontmatter":{"title":"About Project Pythia","content_includes_title":false,"authors":[{"id":"Project Pythia Community","name":"Project Pythia Community"}],"open_access":true,"license":{"content":{"id":"CC-BY-4.0","url":"https://creativecommons.org/licenses/by/4.0/","name":"Creative Commons Attribution 4.0 International","free":true,"CC":true},"code":{"id":"Apache-2.0","url":"https://opensource.org/licenses/Apache-2.0","name":"Apache License 2.0","free":true,"osi":true}},"github":"https://github.com/projectpythia/projectpythia.github.io","affiliations":[{"id":"UAlbany","name":"University at Albany (SUNY)","department":"Atmospheric and Environmental Sciences","url":"https://www.albany.edu/daes"},{"id":"CISL","name":"NSF National Center for Atmospheric Research","department":"Computational and Information Systems Lab","url":"https://www.cisl.ucar.edu"},{"id":"Unidata","name":"NSF Unidata","url":"https://www.unidata.ucar.edu"},{"id":"Argonne","name":"Argonne National Laboratory","department":"Environmental Science Division","url":"https://www.anl.gov/evs"},{"id":"CarbonPlan","name":"CarbonPlan","url":"https://carbonplan.org"},{"id":"NVIDIA","name":"NVIDIA Corporation","url":"https://www.nvidia.com/"},{"id":"2i2c","name":"2i2c","url":"https://2i2c.org"}],"source_url":"https://github.com/projectpythia/projectpythia.github.io/blob/main/portal/about.md","edit_url":"https://github.com/projectpythia/projectpythia.github.io/edit/main/portal/about.md","exports":[{"format":"md","filename":"about.md","url":"/_preview/583/build/about-2f16ef075cfc829a3e5a497b877a99db.md"}]},"mdast":{"type":"root","children":[{"type":"block","children":[{"type":"paragraph","position":{"start":{"line":3,"column":1},"end":{"line":6,"column":1}},"children":[{"type":"text","value":"Project Pythia is the education working group for ","position":{"start":{"line":3,"column":1},"end":{"line":3,"column":1}},"key":"VsjFqYrEzk"},{"type":"link","url":"https://pangeo.io","position":{"start":{"line":3,"column":1},"end":{"line":3,"column":1}},"children":[{"type":"text","value":"Pangeo","position":{"start":{"line":3,"column":1},"end":{"line":3,"column":1}},"key":"q9KZALDwpo"}],"urlSource":"https://pangeo.io","key":"gKzmpQC5vr"},{"type":"text","value":"\nand is an educational resource for the entire geoscience community.\nProject Pythia is a home for Python-centered learning resources that are ","position":{"start":{"line":3,"column":1},"end":{"line":3,"column":1}},"key":"chgDn5loxl"},{"type":"emphasis","position":{"start":{"line":3,"column":1},"end":{"line":3,"column":1}},"children":[{"type":"text","value":"open-source","position":{"start":{"line":3,"column":1},"end":{"line":3,"column":1}},"key":"pnL7HRaa4Y"}],"key":"CW8MOr5kmP"},{"type":"text","value":",\n","position":{"start":{"line":3,"column":1},"end":{"line":3,"column":1}},"key":"zyPyiVmvrd"},{"type":"emphasis","position":{"start":{"line":3,"column":1},"end":{"line":3,"column":1}},"children":[{"type":"text","value":"community-owned","position":{"start":{"line":3,"column":1},"end":{"line":3,"column":1}},"key":"f4ak6qefwJ"}],"key":"aVQ6AzcRTQ"},{"type":"text","value":", ","position":{"start":{"line":3,"column":1},"end":{"line":3,"column":1}},"key":"Sfw0I2lgfx"},{"type":"emphasis","position":{"start":{"line":3,"column":1},"end":{"line":3,"column":1}},"children":[{"type":"text","value":"geoscience-focused","position":{"start":{"line":3,"column":1},"end":{"line":3,"column":1}},"key":"pJYv7lMvhX"}],"key":"G1raUqcYY1"},{"type":"text","value":", and ","position":{"start":{"line":3,"column":1},"end":{"line":3,"column":1}},"key":"hLX9NjOfUx"},{"type":"emphasis","position":{"start":{"line":3,"column":1},"end":{"line":3,"column":1}},"children":[{"type":"text","value":"high-quality","position":{"start":{"line":3,"column":1},"end":{"line":3,"column":1}},"key":"fSQMALY6Fo"}],"key":"OneiAnI9H2"},{"type":"text","value":".","position":{"start":{"line":3,"column":1},"end":{"line":3,"column":1}},"key":"tL5d5UpbSy"}],"key":"AOaQn4H8kc"},{"type":"heading","depth":2,"position":{"start":{"line":8,"column":1},"end":{"line":8,"column":1}},"children":[{"type":"text","value":"Why do we need Project Pythia?","position":{"start":{"line":8,"column":1},"end":{"line":8,"column":1}},"key":"O0iF8AenL9"}],"identifier":"why-do-we-need-project-pythia","label":"Why do we need Project Pythia?","html_id":"why-do-we-need-project-pythia","implicit":true,"key":"DV6pXopcWO"},{"type":"paragraph","position":{"start":{"line":10,"column":1},"end":{"line":28,"column":1}},"children":[{"type":"text","value":"Scientists working in a multitude of disciplines rely heavily on\ncomputing technologies for their research. Numerical simulations\nrun on supercomputers are used in the study of climate, weather,\natmospheric chemistry, wildfires, space weather, and more. Similarly,\na tremendous volume of digital data produced by numerical simulations,\nor observations made with instruments, are analyzed with the help\nof powerful computers and software. Thus, today’s scientists require\nnot only expertise in their scientific discipline, but also require\nhigh-level technical skills to effectively analyze, manipulate, and\nmake sense of potentially vast volumes of data. Computing environments\nchange rapidly, and two technologies that have emerged and are being\nadopted by scientific communities relatively recently are Cloud\nComputing platforms and a software ecosystem of scientific tools\nbuilt around the open source programming language called Python.\nProject Pythia provides a public, web-accessible training\nresource that will help educate current, and aspiring, earth\nscientists to more effectively use both the Scientific Python\nEcosystem and Cloud Computing to make sense of huge volumes of\nnumerical scientific data.","position":{"start":{"line":10,"column":1},"end":{"line":10,"column":1}},"key":"mdxnLCJomW"}],"key":"lXY7t9yrss"},{"type":"heading","depth":2,"position":{"start":{"line":30,"column":1},"end":{"line":30,"column":1}},"children":[{"type":"text","value":"Why the name ","position":{"start":{"line":30,"column":1},"end":{"line":30,"column":1}},"key":"ixhj8NHD1e"},{"type":"emphasis","position":{"start":{"line":30,"column":1},"end":{"line":30,"column":1}},"children":[{"type":"text","value":"Pythia","position":{"start":{"line":30,"column":1},"end":{"line":30,"column":1}},"key":"wQEXEIdMWI"}],"key":"Xo4bjqYmnh"},{"type":"text","value":"?","position":{"start":{"line":30,"column":1},"end":{"line":30,"column":1}},"key":"g6PV2YsHGF"}],"identifier":"why-the-name-pythia","label":"Why the name Pythia?","html_id":"why-the-name-pythia","implicit":true,"key":"P0niEuuMRW"},{"type":"paragraph","position":{"start":{"line":32,"column":1},"end":{"line":36,"column":1}},"children":[{"type":"text","value":"In ancient Greek mythology, the god ","position":{"start":{"line":32,"column":1},"end":{"line":32,"column":1}},"key":"VlPirqJvbK"},{"type":"link","url":"https://en.wikipedia.org/wiki/Apollo","position":{"start":{"line":32,"column":1},"end":{"line":32,"column":1}},"children":[{"type":"text","value":"Apollo","position":{"start":{"line":32,"column":1},"end":{"line":32,"column":1}},"key":"cPaji5wU4B"}],"urlSource":"https://en.wikipedia.org/wiki/Apollo","data":{"page":"Apollo","wiki":"https://en.wikipedia.org/","lang":"en"},"internal":false,"protocol":"wiki","key":"M5RBjZtRqe"},{"type":"text","value":"\nis said to have slain the monstrous ","position":{"start":{"line":32,"column":1},"end":{"line":32,"column":1}},"key":"fIZGJQR0PP"},{"type":"link","url":"https://en.wikipedia.org/wiki/Python_(mythology)","position":{"start":{"line":32,"column":1},"end":{"line":32,"column":1}},"children":[{"type":"text","value":"Python","position":{"start":{"line":32,"column":1},"end":{"line":32,"column":1}},"key":"JTr9q0uUsT"}],"urlSource":"https://en.wikipedia.org/wiki/Python_(mythology)","data":{"page":"Python_(mythology)","wiki":"https://en.wikipedia.org/","lang":"en"},"internal":false,"protocol":"wiki","key":"gkF8DXV4pE"},{"type":"text","value":".\nApollo’s temple was later served by the ","position":{"start":{"line":32,"column":1},"end":{"line":32,"column":1}},"key":"dkdRm4mLin"},{"type":"link","url":"https://en.wikipedia.org/wiki/Oracle","position":{"start":{"line":32,"column":1},"end":{"line":32,"column":1}},"children":[{"type":"text","value":"Oracle","position":{"start":{"line":32,"column":1},"end":{"line":32,"column":1}},"key":"fYYDa2721I"}],"urlSource":"https://en.wikipedia.org/wiki/Oracle","data":{"page":"Oracle","wiki":"https://en.wikipedia.org/","lang":"en"},"internal":false,"protocol":"wiki","key":"fOLmntcTfQ"},{"type":"text","value":"\nof ","position":{"start":{"line":32,"column":1},"end":{"line":32,"column":1}},"key":"WHIv5GBiJd"},{"type":"link","url":"https://en.wikipedia.org/wiki/Delphi","position":{"start":{"line":32,"column":1},"end":{"line":32,"column":1}},"children":[{"type":"text","value":"Delphi","position":{"start":{"line":32,"column":1},"end":{"line":32,"column":1}},"key":"flcoUspeir"}],"urlSource":"https://en.wikipedia.org/wiki/Delphi","data":{"page":"Delphi","wiki":"https://en.wikipedia.org/","lang":"en"},"internal":false,"protocol":"wiki","key":"WNy1HZpxK5"},{"type":"text","value":",\nwho was known as the ","position":{"start":{"line":32,"column":1},"end":{"line":32,"column":1}},"key":"IrLgkpTlPi"},{"type":"link","url":"https://en.wikipedia.org/wiki/Pythia","position":{"start":{"line":32,"column":1},"end":{"line":32,"column":1}},"children":[{"type":"text","value":"Pythia","position":{"start":{"line":32,"column":1},"end":{"line":32,"column":1}},"key":"SxNQdsNYo1"}],"urlSource":"https://en.wikipedia.org/wiki/Pythia","data":{"page":"Pythia","wiki":"https://en.wikipedia.org/","lang":"en"},"internal":false,"protocol":"wiki","key":"DTXaxAO8iW"},{"type":"text","value":".","position":{"start":{"line":32,"column":1},"end":{"line":32,"column":1}},"key":"OPlCsEGQaJ"}],"key":"cayjJYxzEG"},{"type":"paragraph","position":{"start":{"line":38,"column":1},"end":{"line":40,"column":1}},"children":[{"type":"text","value":"Like the Oracle of old, Project Pythia will help you make sense of things that seem mysterious.\nWe will not, however, ","position":{"start":{"line":38,"column":1},"end":{"line":38,"column":1}},"key":"T7K1RAScle"},{"type":"emphasis","position":{"start":{"line":38,"column":1},"end":{"line":38,"column":1}},"children":[{"type":"text","value":"slay","position":{"start":{"line":38,"column":1},"end":{"line":38,"column":1}},"key":"YVJn2QtrLr"}],"key":"DUQPzKRtA2"},{"type":"text","value":" your ","position":{"start":{"line":38,"column":1},"end":{"line":38,"column":1}},"key":"DCBvzkdTrA"},{"type":"link","url":"https://www.python.org","position":{"start":{"line":38,"column":1},"end":{"line":38,"column":1}},"children":[{"type":"text","value":"Python","position":{"start":{"line":38,"column":1},"end":{"line":38,"column":1}},"key":"vFB3hRGagl"}],"urlSource":"https://www.python.org","key":"T0iTcHpVLO"},{"type":"text","value":",\nbut instead help you ","position":{"start":{"line":38,"column":1},"end":{"line":38,"column":1}},"key":"cjJ9izqHnM"},{"type":"emphasis","position":{"start":{"line":38,"column":1},"end":{"line":38,"column":1}},"children":[{"type":"text","value":"improve","position":{"start":{"line":38,"column":1},"end":{"line":38,"column":1}},"key":"v2uh0yWl0C"}],"key":"wlNjlOvikW"},{"type":"text","value":" it -- and help you to help others do the same!","position":{"start":{"line":38,"column":1},"end":{"line":38,"column":1}},"key":"MccoQfc2iS"}],"key":"xf51jO7VJO"},{"type":"heading","depth":2,"position":{"start":{"line":42,"column":1},"end":{"line":42,"column":1}},"children":[{"type":"text","value":"Who is Project Pythia?","position":{"start":{"line":42,"column":1},"end":{"line":42,"column":1}},"key":"m7kd6atXae"}],"identifier":"who-is-project-pythia","label":"Who is Project Pythia?","html_id":"who-is-project-pythia","implicit":true,"key":"qZOY6Ovb6y"},{"type":"paragraph","position":{"start":{"line":44,"column":1},"end":{"line":45,"column":1}},"children":[{"type":"text","value":"Pythia is an open and welcoming community! Look ","position":{"start":{"line":44,"column":1},"end":{"line":44,"column":1}},"key":"DI2R8UIjSE"},{"type":"crossReference","url":"/","position":{"start":{"line":44,"column":1},"end":{"line":44,"column":1}},"children":[{"type":"text","value":"here","position":{"start":{"line":44,"column":1},"end":{"line":44,"column":1}},"key":"ToxKSINRbv"}],"urlSource":"index.md#join-us","dataUrl":"/index.json","identifier":"join-us","label":"join-us","remote":true,"protocol":"file","kind":"heading","template":"{name}","resolved":true,"html_id":"join-us","key":"EYTZayjKx0"},{"type":"text","value":" for info\non how to get involved.","position":{"start":{"line":44,"column":1},"end":{"line":44,"column":1}},"key":"puAN1K9NnC"}],"key":"VXPlKE5ij5"},{"type":"heading","depth":2,"position":{"start":{"line":47,"column":1},"end":{"line":47,"column":1}},"children":[{"type":"text","value":"Project Pythia Goals","position":{"start":{"line":47,"column":1},"end":{"line":47,"column":1}},"key":"aJ17gTF9eo"}],"identifier":"project-pythia-goals","label":"Project Pythia Goals","html_id":"project-pythia-goals","implicit":true,"key":"GVigx3KSBQ"},{"type":"list","ordered":true,"start":1,"spread":false,"position":{"start":{"line":49,"column":1},"end":{"line":59,"column":1}},"children":[{"type":"listItem","spread":true,"position":{"start":{"line":49,"column":1},"end":{"line":54,"column":1}},"children":[{"type":"paragraph","position":{"start":{"line":49,"column":1},"end":{"line":53,"column":1}},"children":[{"type":"emphasis","position":{"start":{"line":49,"column":1},"end":{"line":49,"column":1}},"children":[{"type":"text","value":"The Pythia Portal:","position":{"start":{"line":49,"column":1},"end":{"line":49,"column":1}},"key":"xKgx7ogYym"}],"key":"pOPCPQs5X1"},{"type":"text","value":" A searchable online portal that\nprovides scientists at any point in their career with educational\ncontent and real-world examples needed to learn how to navigate and\nintegrate the myriad packages within the Python ecosystem for the\ngeosciences.","position":{"start":{"line":49,"column":1},"end":{"line":49,"column":1}},"key":"xt9bFhoGzl"}],"key":"h3mR5f2Taz"}],"key":"Yd1harnXsT"},{"type":"listItem","spread":true,"position":{"start":{"line":55,"column":1},"end":{"line":59,"column":1}},"children":[{"type":"paragraph","position":{"start":{"line":55,"column":1},"end":{"line":58,"column":1}},"children":[{"type":"emphasis","position":{"start":{"line":55,"column":1},"end":{"line":55,"column":1}},"children":[{"type":"text","value":"Cloud-Deployable Pythia Platforms:","position":{"start":{"line":55,"column":1},"end":{"line":55,"column":1}},"key":"xHRwPqCMd4"}],"key":"MVxnkhobR2"},{"type":"text","value":" A light-weight,\nBinder-based platform that will make it possible to launch portal\ncontent in customizable executable environments in the Cloud with\nonly a “single click.”","position":{"start":{"line":55,"column":1},"end":{"line":55,"column":1}},"key":"PWnEwWVVh6"}],"key":"rQ326eamxN"}],"key":"rLQbNEzaO4"}],"key":"zq7WsDQbqV"},{"type":"heading","depth":2,"position":{"start":{"line":60,"column":1},"end":{"line":60,"column":1}},"children":[{"type":"text","value":"Presentations about Project Pythia","position":{"start":{"line":60,"column":1},"end":{"line":60,"column":1}},"key":"ROTSYDjzGd"}],"identifier":"presentations-about-project-pythia","label":"Presentations about Project Pythia","html_id":"presentations-about-project-pythia","implicit":true,"key":"PGeZXIZrh2"},{"type":"paragraph","position":{"start":{"line":62,"column":1},"end":{"line":62,"column":1}},"children":[{"type":"text","value":"To learn more about Project Pythia and its history, see this list of presentations (listed in reverse-chronological order):","position":{"start":{"line":62,"column":1},"end":{"line":62,"column":1}},"key":"r5aYyoCZPm"}],"key":"lYWmrW9p8Y"},{"type":"table","position":{"start":{"line":64,"column":1},"end":{"line":91,"column":1}},"children":[{"type":"tableRow","position":{"start":{"line":64,"column":1},"end":{"line":64,"column":1}},"children":[{"type":"tableCell","header":true,"position":{"start":{"line":64,"column":1},"end":{"line":64,"column":1}},"children":[{"type":"text","value":"Forum","position":{"start":{"line":64,"column":1},"end":{"line":64,"column":1}},"key":"ZKgrb0VpjU"}],"key":"CrilbHNNly"},{"type":"tableCell","header":true,"position":{"start":{"line":64,"column":1},"end":{"line":64,"column":1}},"children":[{"type":"text","value":"Date","position":{"start":{"line":64,"column":1},"end":{"line":64,"column":1}},"key":"pL8f7pnCNY"}],"key":"f8Ke6ZIXM6"},{"type":"tableCell","header":true,"position":{"start":{"line":64,"column":1},"end":{"line":64,"column":1}},"children":[{"type":"text","value":"Presenter","position":{"start":{"line":64,"column":1},"end":{"line":64,"column":1}},"key":"Cjf2InXpHN"}],"key":"WxMhbfPQMb"},{"type":"tableCell","header":true,"position":{"start":{"line":64,"column":1},"end":{"line":64,"column":1}},"children":[{"type":"text","value":"Format","position":{"start":{"line":64,"column":1},"end":{"line":64,"column":1}},"key":"jbSjrwT54M"}],"key":"wzG13gqhlU"},{"type":"tableCell","header":true,"position":{"start":{"line":64,"column":1},"end":{"line":64,"column":1}},"children":[{"type":"text","value":"Title (with link)","position":{"start":{"line":64,"column":1},"end":{"line":64,"column":1}},"key":"t60ah6Mleo"}],"key":"LvyfFtcQLW"}],"key":"OCw9HlLb6V"},{"type":"tableRow","position":{"start":{"line":66,"column":1},"end":{"line":66,"column":1}},"children":[{"type":"tableCell","position":{"start":{"line":66,"column":1},"end":{"line":66,"column":1}},"children":[{"type":"text","value":"Pangeo Showcase","position":{"start":{"line":66,"column":1},"end":{"line":66,"column":1}},"key":"MFxQOBN0dP"}],"key":"Ciysqeeszf"},{"type":"tableCell","position":{"start":{"line":66,"column":1},"end":{"line":66,"column":1}},"children":[{"type":"text","value":"2024-10","position":{"start":{"line":66,"column":1},"end":{"line":66,"column":1}},"key":"aUqocwKWOV"}],"key":"cxDBYeLIhK"},{"type":"tableCell","position":{"start":{"line":66,"column":1},"end":{"line":66,"column":1}},"children":[{"type":"text","value":"Brian Rose","position":{"start":{"line":66,"column":1},"end":{"line":66,"column":1}},"key":"Qotrxo2WKx"}],"key":"CHmgmkTggO"},{"type":"tableCell","position":{"start":{"line":66,"column":1},"end":{"line":66,"column":1}},"children":[{"type":"text","value":"slides","position":{"start":{"line":66,"column":1},"end":{"line":66,"column":1}},"key":"E5kzCqhcUa"}],"key":"ls0t4mNnXn"},{"type":"tableCell","position":{"start":{"line":66,"column":1},"end":{"line":66,"column":1}},"children":[{"type":"link","url":"https://docs.google.com/presentation/d/1-RS9DviJnOzwlRMNv1786UMYJ8PmQU-ohu0vo51NM0Q/edit?usp=sharing","position":{"start":{"line":66,"column":1},"end":{"line":66,"column":1}},"children":[{"type":"text","value":"Project Pythia Cookbooks","position":{"start":{"line":66,"column":1},"end":{"line":66,"column":1}},"key":"UBkInGAbHH"}],"urlSource":"https://docs.google.com/presentation/d/1-RS9DviJnOzwlRMNv1786UMYJ8PmQU-ohu0vo51NM0Q/edit?usp=sharing","key":"K9hP4g19w3"}],"key":"Rqxvgj98Ro"}],"key":"UAV57z74oL"},{"type":"tableRow","position":{"start":{"line":67,"column":1},"end":{"line":67,"column":1}},"children":[{"type":"tableCell","position":{"start":{"line":67,"column":1},"end":{"line":67,"column":1}},"children":[{"type":"text","value":"Ocean Sciences","position":{"start":{"line":67,"column":1},"end":{"line":67,"column":1}},"key":"UTLO5mt0Xs"}],"key":"xxiTDYjfMh"},{"type":"tableCell","position":{"start":{"line":67,"column":1},"end":{"line":67,"column":1}},"children":[{"type":"text","value":"2024-02","position":{"start":{"line":67,"column":1},"end":{"line":67,"column":1}},"key":"gC4xo1hRA5"}],"key":"b2GxnF57Qe"},{"type":"tableCell","position":{"start":{"line":67,"column":1},"end":{"line":67,"column":1}},"children":[{"type":"text","value":"Brian Rose","position":{"start":{"line":67,"column":1},"end":{"line":67,"column":1}},"key":"gbq1WsdsNh"}],"key":"H8lEw9r0Ok"},{"type":"tableCell","position":{"start":{"line":67,"column":1},"end":{"line":67,"column":1}},"children":[{"type":"text","value":"slides","position":{"start":{"line":67,"column":1},"end":{"line":67,"column":1}},"key":"j2XG03cd81"}],"key":"TpLNEw4C6r"},{"type":"tableCell","position":{"start":{"line":67,"column":1},"end":{"line":67,"column":1}},"children":[{"type":"link","url":"https://docs.google.com/presentation/d/1tvABElX-0CgiuzMfY7XFY-gsXzGUXqWV6k2qJeTw5bk/edit?usp=sharing","position":{"start":{"line":67,"column":1},"end":{"line":67,"column":1}},"children":[{"type":"text","value":"The Project Pythia Cookbook Initiative","position":{"start":{"line":67,"column":1},"end":{"line":67,"column":1}},"key":"PQPzWNmVKP"}],"urlSource":"https://docs.google.com/presentation/d/1tvABElX-0CgiuzMfY7XFY-gsXzGUXqWV6k2qJeTw5bk/edit?usp=sharing","key":"uN0NJS927k"}],"key":"NKe3EpZwmR"}],"key":"mtS3bsSrhK"},{"type":"tableRow","position":{"start":{"line":68,"column":1},"end":{"line":68,"column":1}},"children":[{"type":"tableCell","position":{"start":{"line":68,"column":1},"end":{"line":68,"column":1}},"children":[{"type":"text","value":"AMS","position":{"start":{"line":68,"column":1},"end":{"line":68,"column":1}},"key":"xX0xP3fhKc"}],"key":"j9YjbkztxK"},{"type":"tableCell","position":{"start":{"line":68,"column":1},"end":{"line":68,"column":1}},"children":[{"type":"text","value":"2024-01","position":{"start":{"line":68,"column":1},"end":{"line":68,"column":1}},"key":"FsSyZhByNa"}],"key":"Nps5S1tDim"},{"type":"tableCell","position":{"start":{"line":68,"column":1},"end":{"line":68,"column":1}},"children":[{"type":"text","value":"Drew Camron","position":{"start":{"line":68,"column":1},"end":{"line":68,"column":1}},"key":"ASyN3LrIoq"}],"key":"rycGQFISXt"},{"type":"tableCell","position":{"start":{"line":68,"column":1},"end":{"line":68,"column":1}},"children":[{"type":"text","value":"slides","position":{"start":{"line":68,"column":1},"end":{"line":68,"column":1}},"key":"BgWfU8h1cx"}],"key":"leKXdHy81p"},{"type":"tableCell","position":{"start":{"line":68,"column":1},"end":{"line":68,"column":1}},"children":[{"type":"link","url":"https://drive.google.com/file/d/1nZfWWozBKQzVCYpKUqWPX51MEgSAhgfM/view?usp=sharing","position":{"start":{"line":68,"column":1},"end":{"line":68,"column":1}},"children":[{"type":"text","value":"Project Pythia: Three Years of Community Building Through Open Source Technology and Education","position":{"start":{"line":68,"column":1},"end":{"line":68,"column":1}},"key":"skCIwByZCd"}],"urlSource":"https://drive.google.com/file/d/1nZfWWozBKQzVCYpKUqWPX51MEgSAhgfM/view?usp=sharing","key":"AqEwXk2PFQ"}],"key":"y2xirpKlII"}],"key":"fYJXFqedys"},{"type":"tableRow","position":{"start":{"line":69,"column":1},"end":{"line":69,"column":1}},"children":[{"type":"tableCell","position":{"start":{"line":69,"column":1},"end":{"line":69,"column":1}},"children":[{"type":"text","value":"AMS","position":{"start":{"line":69,"column":1},"end":{"line":69,"column":1}},"key":"DvuO0BcyDP"}],"key":"XO1ugCG03T"},{"type":"tableCell","position":{"start":{"line":69,"column":1},"end":{"line":69,"column":1}},"children":[{"type":"text","value":"2024-01","position":{"start":{"line":69,"column":1},"end":{"line":69,"column":1}},"key":"lo10D6Lr8J"}],"key":"O7noQyeClG"},{"type":"tableCell","position":{"start":{"line":69,"column":1},"end":{"line":69,"column":1}},"children":[{"type":"text","value":"Kevin Tyle","position":{"start":{"line":69,"column":1},"end":{"line":69,"column":1}},"key":"HFu9rWfCjC"}],"key":"hB2OlUwns4"},{"type":"tableCell","position":{"start":{"line":69,"column":1},"end":{"line":69,"column":1}},"children":[{"type":"text","value":"slides","position":{"start":{"line":69,"column":1},"end":{"line":69,"column":1}},"key":"lcXkanbhgM"}],"key":"iUC0FVpf9N"},{"type":"tableCell","position":{"start":{"line":69,"column":1},"end":{"line":69,"column":1}},"children":[{"type":"link","url":"https://docs.google.com/presentation/d/1zMsoCg1RMHGZDuLLV0QsZB6NwKE7CKo5_8iFAGDGj6o/edit?usp=drive_link","position":{"start":{"line":69,"column":1},"end":{"line":69,"column":1}},"children":[{"type":"text","value":"Cooking up a Storm with Project Pythia","position":{"start":{"line":69,"column":1},"end":{"line":69,"column":1}},"key":"ClEcWkbOea"}],"urlSource":"https://docs.google.com/presentation/d/1zMsoCg1RMHGZDuLLV0QsZB6NwKE7CKo5_8iFAGDGj6o/edit?usp=drive_link","key":"bVgHWZwz9s"}],"key":"fqF3L86LXk"}],"key":"hwtv0dSVw5"},{"type":"tableRow","position":{"start":{"line":70,"column":1},"end":{"line":70,"column":1}},"children":[{"type":"tableCell","position":{"start":{"line":70,"column":1},"end":{"line":70,"column":1}},"children":[{"type":"text","value":"AMS","position":{"start":{"line":70,"column":1},"end":{"line":70,"column":1}},"key":"ZIUUb1EImS"}],"key":"nSqvu0lc9L"},{"type":"tableCell","position":{"start":{"line":70,"column":1},"end":{"line":70,"column":1}},"children":[{"type":"text","value":"2024-01","position":{"start":{"line":70,"column":1},"end":{"line":70,"column":1}},"key":"mV6zIJykJ6"}],"key":"Z1sQcmChhb"},{"type":"tableCell","position":{"start":{"line":70,"column":1},"end":{"line":70,"column":1}},"children":[{"type":"text","value":"Brian Rose","position":{"start":{"line":70,"column":1},"end":{"line":70,"column":1}},"key":"IHu87PRuSa"}],"key":"kWzAQFvHbK"},{"type":"tableCell","position":{"start":{"line":70,"column":1},"end":{"line":70,"column":1}},"children":[{"type":"text","value":"slides","position":{"start":{"line":70,"column":1},"end":{"line":70,"column":1}},"key":"zncmEd3oQ8"}],"key":"B9bvRgxmzF"},{"type":"tableCell","position":{"start":{"line":70,"column":1},"end":{"line":70,"column":1}},"children":[{"type":"link","url":"https://docs.google.com/presentation/d/1nG3iJr6Q7_ktKHg6PXzna7DMp4HDiFgS7scqjKLtXNA/edit?usp=sharing","position":{"start":{"line":70,"column":1},"end":{"line":70,"column":1}},"children":[{"type":"text","value":"Project Pythia’s vision","position":{"start":{"line":70,"column":1},"end":{"line":70,"column":1}},"key":"lu0fDC5m3P"}],"urlSource":"https://docs.google.com/presentation/d/1nG3iJr6Q7_ktKHg6PXzna7DMp4HDiFgS7scqjKLtXNA/edit?usp=sharing","key":"lIFfABtbVC"}],"key":"A3HiY8lgcL"}],"key":"ZrjAZmoFYL"},{"type":"tableRow","position":{"start":{"line":71,"column":1},"end":{"line":71,"column":1}},"children":[{"type":"tableCell","position":{"start":{"line":71,"column":1},"end":{"line":71,"column":1}},"children":[{"type":"text","value":"AGU","position":{"start":{"line":71,"column":1},"end":{"line":71,"column":1}},"key":"v0fsGEbGbt"}],"key":"QMWykILEoR"},{"type":"tableCell","position":{"start":{"line":71,"column":1},"end":{"line":71,"column":1}},"children":[{"type":"text","value":"2023-12","position":{"start":{"line":71,"column":1},"end":{"line":71,"column":1}},"key":"QfbwENtAWb"}],"key":"akBKN1ocGW"},{"type":"tableCell","position":{"start":{"line":71,"column":1},"end":{"line":71,"column":1}},"children":[{"type":"text","value":"Brian Rose","position":{"start":{"line":71,"column":1},"end":{"line":71,"column":1}},"key":"HTL3aX5W3n"}],"key":"uFJMeLmD85"},{"type":"tableCell","position":{"start":{"line":71,"column":1},"end":{"line":71,"column":1}},"children":[{"type":"text","value":"slides","position":{"start":{"line":71,"column":1},"end":{"line":71,"column":1}},"key":"uBG2kZCiVc"}],"key":"ytwL5wdmez"},{"type":"tableCell","position":{"start":{"line":71,"column":1},"end":{"line":71,"column":1}},"children":[{"type":"link","url":"https://docs.google.com/presentation/d/1J6wgvypXxYZ4uTQHsquyH_tlY6KiQXBcxb3cwdd3FUM/edit?usp=sharing","position":{"start":{"line":71,"column":1},"end":{"line":71,"column":1}},"children":[{"type":"text","value":"The Project Pythia Cookbook Initiative","position":{"start":{"line":71,"column":1},"end":{"line":71,"column":1}},"key":"T00rE6tdmA"}],"urlSource":"https://docs.google.com/presentation/d/1J6wgvypXxYZ4uTQHsquyH_tlY6KiQXBcxb3cwdd3FUM/edit?usp=sharing","key":"RQxZq3WFiN"}],"key":"cq89yxvZDx"}],"key":"iFP1Y8y7tl"},{"type":"tableRow","position":{"start":{"line":72,"column":1},"end":{"line":72,"column":1}},"children":[{"type":"tableCell","position":{"start":{"line":72,"column":1},"end":{"line":72,"column":1}},"children":[{"type":"text","value":"AGU","position":{"start":{"line":72,"column":1},"end":{"line":72,"column":1}},"key":"PqaaMmah8p"}],"key":"jJjHvN2LJs"},{"type":"tableCell","position":{"start":{"line":72,"column":1},"end":{"line":72,"column":1}},"children":[{"type":"text","value":"2023-12","position":{"start":{"line":72,"column":1},"end":{"line":72,"column":1}},"key":"f7tx8Fpm4N"}],"key":"S1xpNC6R0p"},{"type":"tableCell","position":{"start":{"line":72,"column":1},"end":{"line":72,"column":1}},"children":[{"type":"text","value":"Julia Kent","position":{"start":{"line":72,"column":1},"end":{"line":72,"column":1}},"key":"YUz2rTy5U6"}],"key":"SggHrCfkmY"},{"type":"tableCell","position":{"start":{"line":72,"column":1},"end":{"line":72,"column":1}},"children":[{"type":"text","value":"slides","position":{"start":{"line":72,"column":1},"end":{"line":72,"column":1}},"key":"z0R3CyeaRT"}],"key":"YUxkzZvPJR"},{"type":"tableCell","position":{"start":{"line":72,"column":1},"end":{"line":72,"column":1}},"children":[{"type":"link","url":"https://docs.google.com/presentation/d/1wm0RxaswVh_YJFcYsHduONsYiYNLc69f0XuHnP7Vfh8/edit?usp=sharing","position":{"start":{"line":72,"column":1},"end":{"line":72,"column":1}},"children":[{"type":"text","value":"Project Pythia: Empowering Geoscientists through Open-Source, Open-Science Collaboration","position":{"start":{"line":72,"column":1},"end":{"line":72,"column":1}},"key":"GDld9qHsUq"}],"urlSource":"https://docs.google.com/presentation/d/1wm0RxaswVh_YJFcYsHduONsYiYNLc69f0XuHnP7Vfh8/edit?usp=sharing","key":"Tt86pP16S3"}],"key":"ryS5eMo7NO"}],"key":"Aic3zjjq1m"},{"type":"tableRow","position":{"start":{"line":73,"column":1},"end":{"line":73,"column":1}},"children":[{"type":"tableCell","position":{"start":{"line":73,"column":1},"end":{"line":73,"column":1}},"children":[{"type":"text","value":"SciPy","position":{"start":{"line":73,"column":1},"end":{"line":73,"column":1}},"key":"zrIDTwPS2i"}],"key":"nXr1KOofLX"},{"type":"tableCell","position":{"start":{"line":73,"column":1},"end":{"line":73,"column":1}},"children":[{"type":"text","value":"2023-07","position":{"start":{"line":73,"column":1},"end":{"line":73,"column":1}},"key":"Mx6PNpJAd0"}],"key":"R8oBiuaqI7"},{"type":"tableCell","position":{"start":{"line":73,"column":1},"end":{"line":73,"column":1}},"children":[{"type":"text","value":"Kevin Tyle / Drew Camron","position":{"start":{"line":73,"column":1},"end":{"line":73,"column":1}},"key":"H6qreCykUI"}],"key":"oW2UXf3KUP"},{"type":"tableCell","position":{"start":{"line":73,"column":1},"end":{"line":73,"column":1}},"children":[{"type":"text","value":"slides","position":{"start":{"line":73,"column":1},"end":{"line":73,"column":1}},"key":"dzKgB4gIPP"}],"key":"GxiroUWI36"},{"type":"tableCell","position":{"start":{"line":73,"column":1},"end":{"line":73,"column":1}},"children":[{"type":"link","url":"https://drive.google.com/file/d/125Wk3TTImHqSYLkgPNsy4_M_w3aENgLr/view?usp=sharing","position":{"start":{"line":73,"column":1},"end":{"line":73,"column":1}},"children":[{"type":"text","value":"Better (Open-source) Homes and Gardens with Project Pythia","position":{"start":{"line":73,"column":1},"end":{"line":73,"column":1}},"key":"bWq16mjiL4"}],"urlSource":"https://drive.google.com/file/d/125Wk3TTImHqSYLkgPNsy4_M_w3aENgLr/view?usp=sharing","key":"Vh8Fc60uRh"}],"key":"hWlERWyl72"}],"key":"aCeHgJlFGG"},{"type":"tableRow","position":{"start":{"line":74,"column":1},"end":{"line":74,"column":1}},"children":[{"type":"tableCell","position":{"start":{"line":74,"column":1},"end":{"line":74,"column":1}},"children":[{"type":"text","value":"Pythia Cook-off 2023","position":{"start":{"line":74,"column":1},"end":{"line":74,"column":1}},"key":"RowhN5oneg"}],"key":"Np9N5VxQjY"},{"type":"tableCell","position":{"start":{"line":74,"column":1},"end":{"line":74,"column":1}},"children":[{"type":"text","value":"2023-06","position":{"start":{"line":74,"column":1},"end":{"line":74,"column":1}},"key":"vVBZqmPufV"}],"key":"rdgs6FH9rr"},{"type":"tableCell","position":{"start":{"line":74,"column":1},"end":{"line":74,"column":1}},"children":[{"type":"text","value":"Brian Rose / Drew Camron","position":{"start":{"line":74,"column":1},"end":{"line":74,"column":1}},"key":"ZVvTcrWuYI"}],"key":"fZo6hc3vMs"},{"type":"tableCell","position":{"start":{"line":74,"column":1},"end":{"line":74,"column":1}},"children":[{"type":"text","value":"slides","position":{"start":{"line":74,"column":1},"end":{"line":74,"column":1}},"key":"Osme4qcwpg"}],"key":"JHWHZnPhQM"},{"type":"tableCell","position":{"start":{"line":74,"column":1},"end":{"line":74,"column":1}},"children":[{"type":"link","url":"https://docs.google.com/presentation/d/1NUnkZLyf4HXkPfQATjoUAs1s9cQAAtTlmVUMwQQmvMg/edit?usp=sharing","position":{"start":{"line":74,"column":1},"end":{"line":74,"column":1}},"children":[{"type":"text","value":"Cook-off 2023 Introduction: All about Pythia, Cookbooks, and the Cook-off!","position":{"start":{"line":74,"column":1},"end":{"line":74,"column":1}},"key":"cAaBUw9n31"}],"urlSource":"https://docs.google.com/presentation/d/1NUnkZLyf4HXkPfQATjoUAs1s9cQAAtTlmVUMwQQmvMg/edit?usp=sharing","key":"QskPAed6JP"}],"key":"EdwvmOTRTn"}],"key":"RYvShKhVpq"},{"type":"tableRow","position":{"start":{"line":75,"column":1},"end":{"line":75,"column":1}},"children":[{"type":"tableCell","position":{"start":{"line":75,"column":1},"end":{"line":75,"column":1}},"children":[{"type":"text","value":"CI2023 Reproducibility Challenge","position":{"start":{"line":75,"column":1},"end":{"line":75,"column":1}},"key":"j9idbxA9dK"}],"key":"xNO5AxfxJ6"},{"type":"tableCell","position":{"start":{"line":75,"column":1},"end":{"line":75,"column":1}},"children":[{"type":"text","value":"2023-05","position":{"start":{"line":75,"column":1},"end":{"line":75,"column":1}},"key":"FT9xGRsPUe"}],"key":"kbBoXriFPc"},{"type":"tableCell","position":{"start":{"line":75,"column":1},"end":{"line":75,"column":1}},"children":[{"type":"text","value":"Brian Rose","position":{"start":{"line":75,"column":1},"end":{"line":75,"column":1}},"key":"ZpdrP3aGzF"}],"key":"kcz49BNRvJ"},{"type":"tableCell","position":{"start":{"line":75,"column":1},"end":{"line":75,"column":1}},"children":[{"type":"text","value":"slides","position":{"start":{"line":75,"column":1},"end":{"line":75,"column":1}},"key":"nCSdjGXKST"}],"key":"GDt80J8Xn3"},{"type":"tableCell","position":{"start":{"line":75,"column":1},"end":{"line":75,"column":1}},"children":[{"type":"cite","url":"https://doi.org/10.5281/zenodo.7915657","position":{"start":{"line":75,"column":1},"end":{"line":75,"column":1}},"children":[{"type":"text","value":"Project Pythia: Learning Python Geoscience Software","position":{"start":{"line":75,"column":1},"end":{"line":75,"column":1}},"key":"sfdm36INSj"}],"kind":"narrative","label":"https://doi.org/10.5281/zenodo.7915657","identifier":"https://doi.org/10.5281/zenodo.7915657","enumerator":"1","key":"fCRqxrRsfA"}],"key":"d4AeLcYGmN"}],"key":"zP3BlCdyGv"},{"type":"tableRow","position":{"start":{"line":76,"column":1},"end":{"line":76,"column":1}},"children":[{"type":"tableCell","position":{"start":{"line":76,"column":1},"end":{"line":76,"column":1}},"children":[{"type":"text","value":"ISS","position":{"start":{"line":76,"column":1},"end":{"line":76,"column":1}},"key":"g5kl8JN2KY"}],"key":"NI224qJWLg"},{"type":"tableCell","position":{"start":{"line":76,"column":1},"end":{"line":76,"column":1}},"children":[{"type":"text","value":"2023-04","position":{"start":{"line":76,"column":1},"end":{"line":76,"column":1}},"key":"e7IUtDMLhn"}],"key":"ySUUtJysui"},{"type":"tableCell","position":{"start":{"line":76,"column":1},"end":{"line":76,"column":1}},"children":[{"type":"text","value":"Julia Kent","position":{"start":{"line":76,"column":1},"end":{"line":76,"column":1}},"key":"BQ4yQXkMeh"}],"key":"H3D9tCUzCc"},{"type":"tableCell","position":{"start":{"line":76,"column":1},"end":{"line":76,"column":1}},"children":[{"type":"text","value":"slides","position":{"start":{"line":76,"column":1},"end":{"line":76,"column":1}},"key":"TY3IFSstij"}],"key":"ezyIBmyrt2"},{"type":"tableCell","position":{"start":{"line":76,"column":1},"end":{"line":76,"column":1}},"children":[{"type":"link","url":"https://docs.google.com/presentation/d/13MH5968BAfR6IxplGVbM2bSJ6uRoa5Wkzk5axqvmCX4/edit?usp=sharing","position":{"start":{"line":76,"column":1},"end":{"line":76,"column":1}},"children":[{"type":"text","value":"How Project Pythia Leverages GitHub for Community Contributions","position":{"start":{"line":76,"column":1},"end":{"line":76,"column":1}},"key":"vW3x6OH6H6"}],"urlSource":"https://docs.google.com/presentation/d/13MH5968BAfR6IxplGVbM2bSJ6uRoa5Wkzk5axqvmCX4/edit?usp=sharing","key":"DRWyHR964L"}],"key":"FhV8FbceuL"}],"key":"FtTrAZ5vxR"},{"type":"tableRow","position":{"start":{"line":77,"column":1},"end":{"line":77,"column":1}},"children":[{"type":"tableCell","position":{"start":{"line":77,"column":1},"end":{"line":77,"column":1}},"children":[{"type":"text","value":"ESDS forum","position":{"start":{"line":77,"column":1},"end":{"line":77,"column":1}},"key":"weHYawjcxW"}],"key":"GDh1Fr5E2Y"},{"type":"tableCell","position":{"start":{"line":77,"column":1},"end":{"line":77,"column":1}},"children":[{"type":"text","value":"2023-03","position":{"start":{"line":77,"column":1},"end":{"line":77,"column":1}},"key":"HUztOaS2vQ"}],"key":"eAQhVqEJYa"},{"type":"tableCell","position":{"start":{"line":77,"column":1},"end":{"line":77,"column":1}},"children":[{"type":"text","value":"Brian Rose","position":{"start":{"line":77,"column":1},"end":{"line":77,"column":1}},"key":"D0JwGHEKIQ"}],"key":"tMsWQVvytu"},{"type":"tableCell","position":{"start":{"line":77,"column":1},"end":{"line":77,"column":1}},"children":[{"type":"text","value":"slides","position":{"start":{"line":77,"column":1},"end":{"line":77,"column":1}},"key":"YEuClfCbLe"}],"key":"l9H3udfhr1"},{"type":"tableCell","position":{"start":{"line":77,"column":1},"end":{"line":77,"column":1}},"children":[{"type":"link","url":"https://drive.google.com/file/d/1goieS2kjajD93fPSKm6aP2GroNotV9zu/view?usp=sharing","position":{"start":{"line":77,"column":1},"end":{"line":77,"column":1}},"children":[{"type":"text","value":"Project Pythia Cookbooks","position":{"start":{"line":77,"column":1},"end":{"line":77,"column":1}},"key":"zhPiUjgBZx"}],"urlSource":"https://drive.google.com/file/d/1goieS2kjajD93fPSKm6aP2GroNotV9zu/view?usp=sharing","key":"bp0Gp6xJRF"}],"key":"F8ALJ5LRf4"}],"key":"ylus0hByKc"},{"type":"tableRow","position":{"start":{"line":78,"column":1},"end":{"line":78,"column":1}},"children":[{"type":"tableCell","position":{"start":{"line":78,"column":1},"end":{"line":78,"column":1}},"children":[{"type":"text","value":"AMS","position":{"start":{"line":78,"column":1},"end":{"line":78,"column":1}},"key":"c1lbNStPeL"}],"key":"QfdnqAvs68"},{"type":"tableCell","position":{"start":{"line":78,"column":1},"end":{"line":78,"column":1}},"children":[{"type":"text","value":"2023-01","position":{"start":{"line":78,"column":1},"end":{"line":78,"column":1}},"key":"G9XkVTjUL6"}],"key":"KunpHlcbEz"},{"type":"tableCell","position":{"start":{"line":78,"column":1},"end":{"line":78,"column":1}},"children":[{"type":"text","value":"Drew Camron","position":{"start":{"line":78,"column":1},"end":{"line":78,"column":1}},"key":"cEEcB8WH1P"}],"key":"ZeciqsHnDX"},{"type":"tableCell","position":{"start":{"line":78,"column":1},"end":{"line":78,"column":1}},"children":[{"type":"text","value":"talk","position":{"start":{"line":78,"column":1},"end":{"line":78,"column":1}},"key":"WOQb4Z8U0u"}],"key":"q3ImVuAAnc"},{"type":"tableCell","position":{"start":{"line":78,"column":1},"end":{"line":78,"column":1}},"children":[{"type":"link","url":"https://ams.confex.com/ams/103ANNUAL/meetingapp.cgi/Paper/421702","position":{"start":{"line":78,"column":1},"end":{"line":78,"column":1}},"children":[{"type":"text","value":"Project Pythia: A Community Update on Open and Sustainable Geoscientific Python Education","position":{"start":{"line":78,"column":1},"end":{"line":78,"column":1}},"key":"fESwoxwr2f"}],"urlSource":"https://ams.confex.com/ams/103ANNUAL/meetingapp.cgi/Paper/421702","key":"TL923E38ee"}],"key":"eEFfEyzic4"}],"key":"li8Yuciiak"},{"type":"tableRow","position":{"start":{"line":79,"column":1},"end":{"line":79,"column":1}},"children":[{"type":"tableCell","position":{"start":{"line":79,"column":1},"end":{"line":79,"column":1}},"children":[{"type":"text","value":"AMS","position":{"start":{"line":79,"column":1},"end":{"line":79,"column":1}},"key":"h8OkqmQOmP"}],"key":"STtXg9HCGm"},{"type":"tableCell","position":{"start":{"line":79,"column":1},"end":{"line":79,"column":1}},"children":[{"type":"text","value":"2023-01","position":{"start":{"line":79,"column":1},"end":{"line":79,"column":1}},"key":"NVtwJ0wpVD"}],"key":"rWw000yJss"},{"type":"tableCell","position":{"start":{"line":79,"column":1},"end":{"line":79,"column":1}},"children":[{"type":"text","value":"Max Grover","position":{"start":{"line":79,"column":1},"end":{"line":79,"column":1}},"key":"DXeZoHr1cs"}],"key":"A0AfK3iNrg"},{"type":"tableCell","position":{"start":{"line":79,"column":1},"end":{"line":79,"column":1}},"children":[{"type":"text","value":"talk","position":{"start":{"line":79,"column":1},"end":{"line":79,"column":1}},"key":"SoxVB4rEEE"}],"key":"XrgSbeqO26"},{"type":"tableCell","position":{"start":{"line":79,"column":1},"end":{"line":79,"column":1}},"children":[{"type":"link","url":"https://ams.confex.com/ams/103ANNUAL/meetingapp.cgi/Paper/417388","position":{"start":{"line":79,"column":1},"end":{"line":79,"column":1}},"children":[{"type":"text","value":"ARMing the Open Science Community with Radar Cookbooks: from the Colorado Rockies to the Gulf Coast and Beyond","position":{"start":{"line":79,"column":1},"end":{"line":79,"column":1}},"key":"UguQYvLxSv"}],"urlSource":"https://ams.confex.com/ams/103ANNUAL/meetingapp.cgi/Paper/417388","key":"xhFXPhhG1G"}],"key":"INZqVC5GkQ"}],"key":"pFECZZHcyG"},{"type":"tableRow","position":{"start":{"line":80,"column":1},"end":{"line":80,"column":1}},"children":[{"type":"tableCell","position":{"start":{"line":80,"column":1},"end":{"line":80,"column":1}},"children":[{"type":"text","value":"AGU","position":{"start":{"line":80,"column":1},"end":{"line":80,"column":1}},"key":"i7kidmCZUj"}],"key":"ZAMS1aFP43"},{"type":"tableCell","position":{"start":{"line":80,"column":1},"end":{"line":80,"column":1}},"children":[{"type":"text","value":"2022-12","position":{"start":{"line":80,"column":1},"end":{"line":80,"column":1}},"key":"k2ii7ClVVS"}],"key":"bfmIQoaNPV"},{"type":"tableCell","position":{"start":{"line":80,"column":1},"end":{"line":80,"column":1}},"children":[{"type":"text","value":"Kevin Tyle","position":{"start":{"line":80,"column":1},"end":{"line":80,"column":1}},"key":"xDDqnJITLf"}],"key":"ksSfZeBI24"},{"type":"tableCell","position":{"start":{"line":80,"column":1},"end":{"line":80,"column":1}},"children":[{"type":"text","value":"slides","position":{"start":{"line":80,"column":1},"end":{"line":80,"column":1}},"key":"UpxEcLwWZw"}],"key":"sKh7SUHGZT"},{"type":"tableCell","position":{"start":{"line":80,"column":1},"end":{"line":80,"column":1}},"children":[{"type":"link","url":"https://eppro01.ativ.me/src/EventPilot/php/express/web/planner.php?id=AGU22","position":{"start":{"line":80,"column":1},"end":{"line":80,"column":1}},"children":[{"type":"text","value":"Project Pythia - Transforming Software Engineering Education for GeoScience","position":{"start":{"line":80,"column":1},"end":{"line":80,"column":1}},"key":"GNCQLxzI6D"}],"urlSource":"https://eppro01.ativ.me/src/EventPilot/php/express/web/planner.php?id=AGU22","key":"AUFRlbPOBw"}],"key":"muLGw7UCF0"}],"key":"feUVj2F6dM"},{"type":"tableRow","position":{"start":{"line":81,"column":1},"end":{"line":81,"column":1}},"children":[{"type":"tableCell","position":{"start":{"line":81,"column":1},"end":{"line":81,"column":1}},"children":[{"type":"text","value":"AGU","position":{"start":{"line":81,"column":1},"end":{"line":81,"column":1}},"key":"LuTHsGHglF"}],"key":"QbKtBgVvFv"},{"type":"tableCell","position":{"start":{"line":81,"column":1},"end":{"line":81,"column":1}},"children":[{"type":"text","value":"2022-12","position":{"start":{"line":81,"column":1},"end":{"line":81,"column":1}},"key":"KpQUNUQqCr"}],"key":"lHhu2AnB8N"},{"type":"tableCell","position":{"start":{"line":81,"column":1},"end":{"line":81,"column":1}},"children":[{"type":"text","value":"Julia Kent","position":{"start":{"line":81,"column":1},"end":{"line":81,"column":1}},"key":"KVY8gDc1a6"}],"key":"O0re1OtALk"},{"type":"tableCell","position":{"start":{"line":81,"column":1},"end":{"line":81,"column":1}},"children":[{"type":"text","value":"slides","position":{"start":{"line":81,"column":1},"end":{"line":81,"column":1}},"key":"PwraLXpTjG"}],"key":"vLzFeNEyvs"},{"type":"tableCell","position":{"start":{"line":81,"column":1},"end":{"line":81,"column":1}},"children":[{"type":"link","url":"https://docs.google.com/presentation/d/19oWV7LULijtIYObrNW3ccoRLNFV9lYA0APuPlXAx_z8/edit?usp=sharing","position":{"start":{"line":81,"column":1},"end":{"line":81,"column":1}},"children":[{"type":"text","value":"Project Pythia: A Pangeo Community Tool for Open-Source Education","position":{"start":{"line":81,"column":1},"end":{"line":81,"column":1}},"key":"mwPsn6WVSG"}],"urlSource":"https://docs.google.com/presentation/d/19oWV7LULijtIYObrNW3ccoRLNFV9lYA0APuPlXAx_z8/edit?usp=sharing","key":"qPEWqWJiwh"}],"key":"g4HdEeWLrx"}],"key":"Ex352CJiHN"},{"type":"tableRow","position":{"start":{"line":82,"column":1},"end":{"line":82,"column":1}},"children":[{"type":"tableCell","position":{"start":{"line":82,"column":1},"end":{"line":82,"column":1}},"children":[{"type":"text","value":"SciPy","position":{"start":{"line":82,"column":1},"end":{"line":82,"column":1}},"key":"TB8IzmOJ1s"}],"key":"TzAFaETyal"},{"type":"tableCell","position":{"start":{"line":82,"column":1},"end":{"line":82,"column":1}},"children":[{"type":"text","value":"2022-07","position":{"start":{"line":82,"column":1},"end":{"line":82,"column":1}},"key":"HLLkvCaHbd"}],"key":"EC3l0uaHy7"},{"type":"tableCell","position":{"start":{"line":82,"column":1},"end":{"line":82,"column":1}},"children":[{"type":"text","value":"Kevin Tyle","position":{"start":{"line":82,"column":1},"end":{"line":82,"column":1}},"key":"IvynOZm7Am"}],"key":"bzFjJ8XGbD"},{"type":"tableCell","position":{"start":{"line":82,"column":1},"end":{"line":82,"column":1}},"children":[{"type":"text","value":"slides","position":{"start":{"line":82,"column":1},"end":{"line":82,"column":1}},"key":"SWyxS2jIRv"}],"key":"yFvxEZvLQd"},{"type":"tableCell","position":{"start":{"line":82,"column":1},"end":{"line":82,"column":1}},"children":[{"type":"link","url":"https://docs.google.com/presentation/d/1tyPkDVDKZX5BsWk9j-TTwiKT8mNQBBZG/edit?usp=sharing&ouid=114646835079460879999&rtpof=true&sd=true","position":{"start":{"line":82,"column":1},"end":{"line":82,"column":1}},"children":[{"type":"text","value":"A Community-built Training Resource for the Geoscientific Python Software Ecosystem","position":{"start":{"line":82,"column":1},"end":{"line":82,"column":1}},"key":"aq7yic1299"}],"urlSource":"https://docs.google.com/presentation/d/1tyPkDVDKZX5BsWk9j-TTwiKT8mNQBBZG/edit?usp=sharing&ouid=114646835079460879999&rtpof=true&sd=true","key":"C9Xbon8QhM"}],"key":"iY8lRJ52BQ"}],"key":"jl0egp2Q9F"},{"type":"tableRow","position":{"start":{"line":83,"column":1},"end":{"line":83,"column":1}},"children":[{"type":"tableCell","position":{"start":{"line":83,"column":1},"end":{"line":83,"column":1}},"children":[{"type":"text","value":"ESDS forum","position":{"start":{"line":83,"column":1},"end":{"line":83,"column":1}},"key":"u5chxKkW3G"}],"key":"dWG8TzO00L"},{"type":"tableCell","position":{"start":{"line":83,"column":1},"end":{"line":83,"column":1}},"children":[{"type":"text","value":"2022-05","position":{"start":{"line":83,"column":1},"end":{"line":83,"column":1}},"key":"Ae1U37i6d1"}],"key":"d7NufFsIbv"},{"type":"tableCell","position":{"start":{"line":83,"column":1},"end":{"line":83,"column":1}},"children":[{"type":"text","value":"Julia Kent","position":{"start":{"line":83,"column":1},"end":{"line":83,"column":1}},"key":"JTN8ZITUZ4"}],"key":"N7Po8SEOP9"},{"type":"tableCell","position":{"start":{"line":83,"column":1},"end":{"line":83,"column":1}},"children":[{"type":"text","value":"slides","position":{"start":{"line":83,"column":1},"end":{"line":83,"column":1}},"key":"Jkq55z80mj"}],"key":"wUdcAgEaLz"},{"type":"tableCell","position":{"start":{"line":83,"column":1},"end":{"line":83,"column":1}},"children":[{"type":"link","url":"https://docs.google.com/presentation/d/1NGLFwqJdsu53CtsCqZLO3dxQtRcelOsm/edit?usp=sharing&ouid=107342162699810699865&rtpof=true&sd=true","position":{"start":{"line":83,"column":1},"end":{"line":83,"column":1}},"children":[{"type":"text","value":"Project Pythia: A Community Learning Resource for Geoscientists","position":{"start":{"line":83,"column":1},"end":{"line":83,"column":1}},"key":"ACaXHuUqod"}],"urlSource":"https://docs.google.com/presentation/d/1NGLFwqJdsu53CtsCqZLO3dxQtRcelOsm/edit?usp=sharing&ouid=107342162699810699865&rtpof=true&sd=true","key":"n3AmrQpE8V"}],"key":"m4v1xfNOvY"}],"key":"URnXovOO6g"},{"type":"tableRow","position":{"start":{"line":84,"column":1},"end":{"line":84,"column":1}},"children":[{"type":"tableCell","position":{"start":{"line":84,"column":1},"end":{"line":84,"column":1}},"children":[{"type":"text","value":"AMS","position":{"start":{"line":84,"column":1},"end":{"line":84,"column":1}},"key":"DtIn1N4Wvd"}],"key":"S3fKzeTXSL"},{"type":"tableCell","position":{"start":{"line":84,"column":1},"end":{"line":84,"column":1}},"children":[{"type":"text","value":"2022-01","position":{"start":{"line":84,"column":1},"end":{"line":84,"column":1}},"key":"AA4onRHdxx"}],"key":"yz2cg1G5mZ"},{"type":"tableCell","position":{"start":{"line":84,"column":1},"end":{"line":84,"column":1}},"children":[{"type":"text","value":"Drew Camron","position":{"start":{"line":84,"column":1},"end":{"line":84,"column":1}},"key":"XlgDWHapE1"}],"key":"kDjSJavMsI"},{"type":"tableCell","position":{"start":{"line":84,"column":1},"end":{"line":84,"column":1}},"children":[{"type":"text","value":"slides","position":{"start":{"line":84,"column":1},"end":{"line":84,"column":1}},"key":"WHNLDA94C5"}],"key":"WsFoarpA30"},{"type":"tableCell","position":{"start":{"line":84,"column":1},"end":{"line":84,"column":1}},"children":[{"type":"link","url":"https://docs.google.com/presentation/d/1NuV5sI3oGhvuUt_s8hzmj0UA9MqCtlxWTADbJHjr9ow/edit?usp=sharing","position":{"start":{"line":84,"column":1},"end":{"line":84,"column":1}},"children":[{"type":"text","value":"Project Pythia: A community update","position":{"start":{"line":84,"column":1},"end":{"line":84,"column":1}},"key":"H3yYz9lCee"}],"urlSource":"https://docs.google.com/presentation/d/1NuV5sI3oGhvuUt_s8hzmj0UA9MqCtlxWTADbJHjr9ow/edit?usp=sharing","key":"UyvacEwJue"}],"key":"KrixAbGmvQ"}],"key":"Rjnb3vt69D"},{"type":"tableRow","position":{"start":{"line":85,"column":1},"end":{"line":85,"column":1}},"children":[{"type":"tableCell","position":{"start":{"line":85,"column":1},"end":{"line":85,"column":1}},"children":[{"type":"text","value":"AMS","position":{"start":{"line":85,"column":1},"end":{"line":85,"column":1}},"key":"hMgnh8rVLd"}],"key":"KGuIPq2Olr"},{"type":"tableCell","position":{"start":{"line":85,"column":1},"end":{"line":85,"column":1}},"children":[{"type":"text","value":"2022-01","position":{"start":{"line":85,"column":1},"end":{"line":85,"column":1}},"key":"cYK490mFAW"}],"key":"YyCNucDvKV"},{"type":"tableCell","position":{"start":{"line":85,"column":1},"end":{"line":85,"column":1}},"children":[{"type":"text","value":"Kevin Tyle","position":{"start":{"line":85,"column":1},"end":{"line":85,"column":1}},"key":"kTjEVVfW5c"}],"key":"KrXsZCnPvX"},{"type":"tableCell","position":{"start":{"line":85,"column":1},"end":{"line":85,"column":1}},"children":[{"type":"text","value":"slides","position":{"start":{"line":85,"column":1},"end":{"line":85,"column":1}},"key":"nQAgGNS56I"}],"key":"Hzi4F7qM9n"},{"type":"tableCell","position":{"start":{"line":85,"column":1},"end":{"line":85,"column":1}},"children":[{"type":"link","url":"https://docs.google.com/presentation/d/1D8kkpsX4CE3rT5QQliH6JfKYeY76fT1gClIEzboxgko/","position":{"start":{"line":85,"column":1},"end":{"line":85,"column":1}},"children":[{"type":"text","value":"Leveraging Project Pythia in an Advanced Geoscience & Visualization Course","position":{"start":{"line":85,"column":1},"end":{"line":85,"column":1}},"key":"kdloYrJzgI"}],"urlSource":"https://docs.google.com/presentation/d/1D8kkpsX4CE3rT5QQliH6JfKYeY76fT1gClIEzboxgko/","key":"iYakrYmCRg"}],"key":"PwjqhnOSZG"}],"key":"xqqtBGPBb6"},{"type":"tableRow","position":{"start":{"line":86,"column":1},"end":{"line":86,"column":1}},"children":[{"type":"tableCell","position":{"start":{"line":86,"column":1},"end":{"line":86,"column":1}},"children":[{"type":"text","value":"AMS","position":{"start":{"line":86,"column":1},"end":{"line":86,"column":1}},"key":"n98y3Uj2qi"}],"key":"GCtXRAMkHl"},{"type":"tableCell","position":{"start":{"line":86,"column":1},"end":{"line":86,"column":1}},"children":[{"type":"text","value":"2022-01","position":{"start":{"line":86,"column":1},"end":{"line":86,"column":1}},"key":"EaT2uNyBGd"}],"key":"rTtMLzNFXO"},{"type":"tableCell","position":{"start":{"line":86,"column":1},"end":{"line":86,"column":1}},"children":[{"type":"text","value":"Max Grover","position":{"start":{"line":86,"column":1},"end":{"line":86,"column":1}},"key":"PVBgcDhDKU"}],"key":"ndBj5KLnhg"},{"type":"tableCell","position":{"start":{"line":86,"column":1},"end":{"line":86,"column":1}},"children":[{"type":"text","value":"slides","position":{"start":{"line":86,"column":1},"end":{"line":86,"column":1}},"key":"AY9XIP077y"}],"key":"JxOXGw76D0"},{"type":"tableCell","position":{"start":{"line":86,"column":1},"end":{"line":86,"column":1}},"children":[{"type":"link","url":"https://docs.google.com/presentation/d/1aTw0DmaZ-7PQtWXxQqdik825r5mOoYRe/edit?usp=sharing&ouid=113419461755911727326&rtpof=true&sd=true","position":{"start":{"line":86,"column":1},"end":{"line":86,"column":1}},"children":[{"type":"text","value":"Rethinking CESM Diagnostics through the Lens of Earth System Data Science","position":{"start":{"line":86,"column":1},"end":{"line":86,"column":1}},"key":"X1thU5Ip8W"}],"urlSource":"https://docs.google.com/presentation/d/1aTw0DmaZ-7PQtWXxQqdik825r5mOoYRe/edit?usp=sharing&ouid=113419461755911727326&rtpof=true&sd=true","key":"OZ6xDgBqK2"}],"key":"V9pqmKjBEW"}],"key":"fG9ESeuUrE"},{"type":"tableRow","position":{"start":{"line":87,"column":1},"end":{"line":87,"column":1}},"children":[{"type":"tableCell","position":{"start":{"line":87,"column":1},"end":{"line":87,"column":1}},"children":[{"type":"text","value":"AGU","position":{"start":{"line":87,"column":1},"end":{"line":87,"column":1}},"key":"E69rdC7FPa"}],"key":"iIBgLgm1w6"},{"type":"tableCell","position":{"start":{"line":87,"column":1},"end":{"line":87,"column":1}},"children":[{"type":"text","value":"2021-12","position":{"start":{"line":87,"column":1},"end":{"line":87,"column":1}},"key":"zBUYm0J0fn"}],"key":"hFsDB1RkCT"},{"type":"tableCell","position":{"start":{"line":87,"column":1},"end":{"line":87,"column":1}},"children":[{"type":"text","value":"Kevin Paul","position":{"start":{"line":87,"column":1},"end":{"line":87,"column":1}},"key":"qq9kcL2970"}],"key":"oNkVZv4YVj"},{"type":"tableCell","position":{"start":{"line":87,"column":1},"end":{"line":87,"column":1}},"children":[{"type":"text","value":"e-poster","position":{"start":{"line":87,"column":1},"end":{"line":87,"column":1}},"key":"on3kRXoOFc"}],"key":"eECUH4IYwV"},{"type":"tableCell","position":{"start":{"line":87,"column":1},"end":{"line":87,"column":1}},"children":[{"type":"link","url":"https://agu2021fallmeeting-agu.ipostersessions.com/Default.aspx?s=CF-91-F4-F8-35-E4-B7-40-F2-8C-F6-86-76-97-11-02","position":{"start":{"line":87,"column":1},"end":{"line":87,"column":1}},"children":[{"type":"text","value":"Pangeo and Project Pythia: Helping Geoscientists Navigate the Scientific Python Ecosystem","position":{"start":{"line":87,"column":1},"end":{"line":87,"column":1}},"key":"d3SEidSZI3"}],"urlSource":"https://agu2021fallmeeting-agu.ipostersessions.com/Default.aspx?s=CF-91-F4-F8-35-E4-B7-40-F2-8C-F6-86-76-97-11-02","key":"pma8Tu4pFC"}],"key":"g1MPn9m6cQ"}],"key":"y0DwWHFNAU"},{"type":"tableRow","position":{"start":{"line":88,"column":1},"end":{"line":88,"column":1}},"children":[{"type":"tableCell","position":{"start":{"line":88,"column":1},"end":{"line":88,"column":1}},"children":[{"type":"text","value":"AGU","position":{"start":{"line":88,"column":1},"end":{"line":88,"column":1}},"key":"MtKNPbIn8n"}],"key":"LHPokEiXN3"},{"type":"tableCell","position":{"start":{"line":88,"column":1},"end":{"line":88,"column":1}},"children":[{"type":"text","value":"2021-12","position":{"start":{"line":88,"column":1},"end":{"line":88,"column":1}},"key":"XMyrTudGbx"}],"key":"IkJjdiUWjb"},{"type":"tableCell","position":{"start":{"line":88,"column":1},"end":{"line":88,"column":1}},"children":[{"type":"text","value":"Kevin Paul","position":{"start":{"line":88,"column":1},"end":{"line":88,"column":1}},"key":"MDp0rIFTVY"}],"key":"m4m6xtxHgU"},{"type":"tableCell","position":{"start":{"line":88,"column":1},"end":{"line":88,"column":1}},"children":[{"type":"text","value":"e-poster","position":{"start":{"line":88,"column":1},"end":{"line":88,"column":1}},"key":"zhbGmrGyjW"}],"key":"TZYGj4gonQ"},{"type":"tableCell","position":{"start":{"line":88,"column":1},"end":{"line":88,"column":1}},"children":[{"type":"link","url":"https://agu2021fallmeeting-agu.ipostersessions.com/Default.aspx?s=25-22-8E-6D-6E-CB-B4-E9-6D-08-78-2A-61-2F-62-09","position":{"start":{"line":88,"column":1},"end":{"line":88,"column":1}},"children":[{"type":"text","value":"Project Pythia: A Resource to Help Geoscientists Navigate the Scientific Python Ecosystem","position":{"start":{"line":88,"column":1},"end":{"line":88,"column":1}},"key":"ROZ44cZTbM"}],"urlSource":"https://agu2021fallmeeting-agu.ipostersessions.com/Default.aspx?s=25-22-8E-6D-6E-CB-B4-E9-6D-08-78-2A-61-2F-62-09","key":"cWZ3dID01r"}],"key":"JTwzdHlxyW"}],"key":"Q8IiqWx1f4"},{"type":"tableRow","position":{"start":{"line":89,"column":1},"end":{"line":89,"column":1}},"children":[{"type":"tableCell","position":{"start":{"line":89,"column":1},"end":{"line":89,"column":1}},"children":[{"type":"text","value":"AGU","position":{"start":{"line":89,"column":1},"end":{"line":89,"column":1}},"key":"NR4Po95CDe"}],"key":"QK1sq0f8V0"},{"type":"tableCell","position":{"start":{"line":89,"column":1},"end":{"line":89,"column":1}},"children":[{"type":"text","value":"2021-12","position":{"start":{"line":89,"column":1},"end":{"line":89,"column":1}},"key":"MfcpYGr4TB"}],"key":"Chih8M3n6p"},{"type":"tableCell","position":{"start":{"line":89,"column":1},"end":{"line":89,"column":1}},"children":[{"type":"text","value":"Julia Kent","position":{"start":{"line":89,"column":1},"end":{"line":89,"column":1}},"key":"i9MSjGOXju"}],"key":"luYvSwsAc2"},{"type":"tableCell","position":{"start":{"line":89,"column":1},"end":{"line":89,"column":1}},"children":[{"type":"text","value":"abstract","position":{"start":{"line":89,"column":1},"end":{"line":89,"column":1}},"key":"pXioUzF2A5"}],"key":"O1OCsVUEhk"},{"type":"tableCell","position":{"start":{"line":89,"column":1},"end":{"line":89,"column":1}},"children":[{"type":"link","url":"https://t.co/hQ1wGQZB18","position":{"start":{"line":89,"column":1},"end":{"line":89,"column":1}},"children":[{"type":"text","value":"ESDS Educational Efforts","position":{"start":{"line":89,"column":1},"end":{"line":89,"column":1}},"key":"VeYVu8vLcP"}],"urlSource":"https://t.co/hQ1wGQZB18","key":"PzpCPDkTKx"}],"key":"zlf7c4jOTE"}],"key":"wInbhPbUVP"},{"type":"tableRow","position":{"start":{"line":90,"column":1},"end":{"line":90,"column":1}},"children":[{"type":"tableCell","position":{"start":{"line":90,"column":1},"end":{"line":90,"column":1}},"children":[{"type":"text","value":"Pangeo Showcase","position":{"start":{"line":90,"column":1},"end":{"line":90,"column":1}},"key":"gcNc4yDCU1"}],"key":"iPv6bLcJ2n"},{"type":"tableCell","position":{"start":{"line":90,"column":1},"end":{"line":90,"column":1}},"children":[{"type":"text","value":"2021-06","position":{"start":{"line":90,"column":1},"end":{"line":90,"column":1}},"key":"m31pp8ROG3"}],"key":"yefqbUmLjt"},{"type":"tableCell","position":{"start":{"line":90,"column":1},"end":{"line":90,"column":1}},"children":[{"type":"text","value":"Brian Rose","position":{"start":{"line":90,"column":1},"end":{"line":90,"column":1}},"key":"r8qLktNpit"}],"key":"q1yYB182YP"},{"type":"tableCell","position":{"start":{"line":90,"column":1},"end":{"line":90,"column":1}},"children":[{"type":"text","value":"video + slides","position":{"start":{"line":90,"column":1},"end":{"line":90,"column":1}},"key":"vqHclsQT50"}],"key":"a43BqT4Fho"},{"type":"tableCell","position":{"start":{"line":90,"column":1},"end":{"line":90,"column":1}},"children":[{"type":"link","url":"https://discourse.pangeo.io/t/june-23-2021-project-pythia-a-community-learning-resource-for-python-based-computing-in-the-geosciences/1601","position":{"start":{"line":90,"column":1},"end":{"line":90,"column":1}},"children":[{"type":"text","value":"Project Pythia: a community learning resource for Python-based computing in the geosciences","position":{"start":{"line":90,"column":1},"end":{"line":90,"column":1}},"key":"qkFWIHPKXZ"}],"urlSource":"https://discourse.pangeo.io/t/june-23-2021-project-pythia-a-community-learning-resource-for-python-based-computing-in-the-geosciences/1601","key":"CGMvRsjest"}],"key":"GkbkK6JHCb"}],"key":"ljMAy6ZHtg"},{"type":"tableRow","position":{"start":{"line":91,"column":1},"end":{"line":91,"column":1}},"children":[{"type":"tableCell","position":{"start":{"line":91,"column":1},"end":{"line":91,"column":1}},"children":[{"type":"text","value":"AMS","position":{"start":{"line":91,"column":1},"end":{"line":91,"column":1}},"key":"z1YcObi9V2"}],"key":"EcyXwTIvi0"},{"type":"tableCell","position":{"start":{"line":91,"column":1},"end":{"line":91,"column":1}},"children":[{"type":"text","value":"2021-01","position":{"start":{"line":91,"column":1},"end":{"line":91,"column":1}},"key":"ZJUqAk9jRO"}],"key":"RzIvc9bMRc"},{"type":"tableCell","position":{"start":{"line":91,"column":1},"end":{"line":91,"column":1}},"children":[{"type":"text","value":"John Clyne","position":{"start":{"line":91,"column":1},"end":{"line":91,"column":1}},"key":"B0vVXI4PdP"}],"key":"mTfll1cl36"},{"type":"tableCell","position":{"start":{"line":91,"column":1},"end":{"line":91,"column":1}},"children":[{"type":"text","value":"video","position":{"start":{"line":91,"column":1},"end":{"line":91,"column":1}},"key":"fvCDh8EaDM"}],"key":"Euw3vWwXg1"},{"type":"tableCell","position":{"start":{"line":91,"column":1},"end":{"line":91,"column":1}},"children":[{"type":"link","url":"https://youtu.be/_UxlrwB_evo","position":{"start":{"line":91,"column":1},"end":{"line":91,"column":1}},"children":[{"type":"text","value":"Project Pythia: a community learning resource for geoscientists","position":{"start":{"line":91,"column":1},"end":{"line":91,"column":1}},"key":"FdW3dCQMld"}],"urlSource":"https://youtu.be/_UxlrwB_evo","key":"qAXCZ2VTxe"}],"key":"bJMxyLyAAv"}],"key":"voykGTd0Hb"}],"key":"M6RXWCPyMx"}],"key":"gPFeIueUCL"}],"key":"Mg5XaxKiXO"},"references":{"cite":{"order":["https://doi.org/10.5281/zenodo.7915657"],"data":{"https://doi.org/10.5281/zenodo.7915657":{"label":"https://doi.org/10.5281/zenodo.7915657","enumerator":"1","doi":"10.5281/ZENODO.7915657","html":"Rose, B. (2023). <i>CI2023 Reproducibility Challenge - Talk with the Expert | Open-source software: Project Pythia, Brian Rose</i>. <a target=\"_blank\" rel=\"noreferrer\" href=\"https://doi.org/10.5281/ZENODO.7915657\">10.5281/ZENODO.7915657</a>","url":"https://doi.org/10.5281/ZENODO.7915657"}}}},"footer":{"navigation":{"prev":{"title":"Project Pythia","url":"/","group":"Project Pythia"},"next":{"title":"Blog","url":"/blog","group":"Project Pythia"}}},"domain":"http://localhost:3000"}